{
"meta":{"test_sets":[],"test_metrics":[],"learn_metrics":[{"best_value":"Min","name":"RMSE"}],"launch_mode":"Train","parameters":"","iteration_count":1000,"learn_sets":["learn"],"name":"experiment"},
"iterations":[
{"learn":[14.59871775],"iteration":0,"passed_time":0.166378222,"remaining_time":166.2118437},
{"learn":[14.22518863],"iteration":1,"passed_time":0.1676399545,"remaining_time":83.65233731},
{"learn":[13.8866124],"iteration":2,"passed_time":0.1688841785,"remaining_time":56.12584199},
{"learn":[13.52356875],"iteration":3,"passed_time":0.1712717504,"remaining_time":42.64666585},
{"learn":[13.18870211],"iteration":4,"passed_time":0.1728611898,"remaining_time":34.39937677},
{"learn":[12.9124226],"iteration":5,"passed_time":0.1738228118,"remaining_time":28.79664582},
{"learn":[12.60003351],"iteration":6,"passed_time":0.1750414666,"remaining_time":24.83088234},
{"learn":[12.32990573],"iteration":7,"passed_time":0.1774659593,"remaining_time":22.00577895},
{"learn":[12.0660619],"iteration":8,"passed_time":0.1794274166,"remaining_time":19.7569522},
{"learn":[11.77309809],"iteration":9,"passed_time":0.1803542627,"remaining_time":17.85507201},
{"learn":[11.49227636],"iteration":10,"passed_time":0.1813690522,"remaining_time":16.3067266},
{"learn":[11.26264833],"iteration":11,"passed_time":0.182613234,"remaining_time":15.03515627},
{"learn":[11.04260393],"iteration":12,"passed_time":0.1837436994,"remaining_time":13.95038702},
{"learn":[10.79916926],"iteration":13,"passed_time":0.1846034408,"remaining_time":13.00135662},
{"learn":[10.5541002],"iteration":14,"passed_time":0.1853653667,"remaining_time":12.17232575},
{"learn":[10.31918115],"iteration":15,"passed_time":0.1861988868,"remaining_time":11.45123154},
{"learn":[10.10004441],"iteration":16,"passed_time":0.1872913356,"remaining_time":10.82984605},
{"learn":[9.894556723],"iteration":17,"passed_time":0.1884168673,"remaining_time":10.27918687},
{"learn":[9.690174082],"iteration":18,"passed_time":0.1894713856,"remaining_time":9.782706805},
{"learn":[9.506034866],"iteration":19,"passed_time":0.1902455732,"remaining_time":9.322033085},
{"learn":[9.338524633],"iteration":20,"passed_time":0.1910514913,"remaining_time":8.906638568},
{"learn":[9.170203312],"iteration":21,"passed_time":0.1918174099,"remaining_time":8.527155767},
{"learn":[9.010299969],"iteration":22,"passed_time":0.1924736439,"remaining_time":8.175945655},
{"learn":[8.843866678],"iteration":23,"passed_time":0.1935149853,"remaining_time":7.869609403},
{"learn":[8.690548059],"iteration":24,"passed_time":0.1947785982,"remaining_time":7.59636533},
{"learn":[8.555307687],"iteration":25,"passed_time":0.1956175296,"remaining_time":7.32813361},
{"learn":[8.413851302],"iteration":26,"passed_time":0.1963193747,"remaining_time":7.074768578},
{"learn":[8.29256019],"iteration":27,"passed_time":0.1969943791,"remaining_time":6.838519162},
{"learn":[8.162193833],"iteration":28,"passed_time":0.1976790917,"remaining_time":6.618841311},
{"learn":[8.040736294],"iteration":29,"passed_time":0.1983215159,"remaining_time":6.412395679},
{"learn":[7.921220278],"iteration":30,"passed_time":0.1993068396,"remaining_time":6.22994605},
{"learn":[7.809589039],"iteration":31,"passed_time":0.2008308088,"remaining_time":6.075131967},
{"learn":[7.699675801],"iteration":32,"passed_time":0.2016486664,"remaining_time":5.908916983},
{"learn":[7.60645267],"iteration":33,"passed_time":0.2024853568,"remaining_time":5.752966314},
{"learn":[7.498880302],"iteration":34,"passed_time":0.203254418,"remaining_time":5.604014669},
{"learn":[7.401158744],"iteration":35,"passed_time":0.2041267122,"remaining_time":5.466059739},
{"learn":[7.306431077],"iteration":36,"passed_time":0.2048939289,"remaining_time":5.332779826},
{"learn":[7.223863468],"iteration":37,"passed_time":0.2059636492,"remaining_time":5.214132382},
{"learn":[7.143477682],"iteration":38,"passed_time":0.2075470112,"remaining_time":5.114171226},
{"learn":[7.062817131],"iteration":39,"passed_time":0.2083857637,"remaining_time":5.001258329},
{"learn":[6.990793435],"iteration":40,"passed_time":0.2091202043,"remaining_time":4.891372584},
{"learn":[6.931862224],"iteration":41,"passed_time":0.2098388659,"remaining_time":4.786324609},
{"learn":[6.858296558],"iteration":42,"passed_time":0.210583708,"remaining_time":4.686711826},
{"learn":[6.786268161],"iteration":43,"passed_time":0.2114391181,"remaining_time":4.593995384},
{"learn":[6.717118549],"iteration":44,"passed_time":0.2132540511,"remaining_time":4.525724863},
{"learn":[6.652948106],"iteration":45,"passed_time":0.2140280461,"remaining_time":4.438755564},
{"learn":[6.589686076],"iteration":46,"passed_time":0.2147625096,"remaining_time":4.354652588},
{"learn":[6.531283097],"iteration":47,"passed_time":0.2154602144,"remaining_time":4.273294253},
{"learn":[6.471368031],"iteration":48,"passed_time":0.216199304,"remaining_time":4.19603139},
{"learn":[6.416481395],"iteration":49,"passed_time":0.2170760867,"remaining_time":4.124445648},
{"learn":[6.369870822],"iteration":50,"passed_time":0.2184473037,"remaining_time":4.06483316},
{"learn":[6.325678067],"iteration":51,"passed_time":0.2192579825,"remaining_time":3.997241681},
{"learn":[6.275766122],"iteration":52,"passed_time":0.2200881492,"remaining_time":3.932518439},
{"learn":[6.224773967],"iteration":53,"passed_time":0.2209606843,"remaining_time":3.870903839},
{"learn":[6.182249254],"iteration":54,"passed_time":0.2217863648,"remaining_time":3.810692996},
{"learn":[6.139904173],"iteration":55,"passed_time":0.222529735,"remaining_time":3.751215534},
{"learn":[6.100525536],"iteration":56,"passed_time":0.2233089435,"remaining_time":3.69439182},
{"learn":[6.062568564],"iteration":57,"passed_time":0.2240318878,"remaining_time":3.638586867},
{"learn":[6.030559288],"iteration":58,"passed_time":0.2249178434,"remaining_time":3.587248994},
{"learn":[5.997931376],"iteration":59,"passed_time":0.2255676602,"remaining_time":3.533893344},
{"learn":[5.964103835],"iteration":60,"passed_time":0.2264210605,"remaining_time":3.485399604},
{"learn":[5.933729724],"iteration":61,"passed_time":0.2271739575,"remaining_time":3.436922132},
{"learn":[5.901932711],"iteration":62,"passed_time":0.2279231095,"remaining_time":3.389904026},
{"learn":[5.873727795],"iteration":63,"passed_time":0.2287716111,"remaining_time":3.345784813},
{"learn":[5.846485734],"iteration":64,"passed_time":0.2304277419,"remaining_time":3.314614441},
{"learn":[5.820630862],"iteration":65,"passed_time":0.2321105834,"remaining_time":3.284716438},
{"learn":[5.793646238],"iteration":66,"passed_time":0.2329316347,"remaining_time":3.243659928},
{"learn":[5.765388646],"iteration":67,"passed_time":0.2337726946,"remaining_time":3.204061049},
{"learn":[5.747073912],"iteration":68,"passed_time":0.2345079604,"remaining_time":3.164158132},
{"learn":[5.722315217],"iteration":69,"passed_time":0.2352774426,"remaining_time":3.125828881},
{"learn":[5.699970599],"iteration":70,"passed_time":0.2362148269,"remaining_time":3.090754566},
{"learn":[5.682732647],"iteration":71,"passed_time":0.2369825551,"remaining_time":3.054441821},
{"learn":[5.663525791],"iteration":72,"passed_time":0.2376208639,"remaining_time":3.017459464},
{"learn":[5.642381613],"iteration":73,"passed_time":0.2385191732,"remaining_time":2.984712898},
{"learn":[5.621404779],"iteration":74,"passed_time":0.2395120473,"remaining_time":2.953981916},
{"learn":[5.602460129],"iteration":75,"passed_time":0.2402326262,"remaining_time":2.920722982},
{"learn":[5.587337574],"iteration":76,"passed_time":0.2408918689,"remaining_time":2.887573961},
{"learn":[5.572393026],"iteration":77,"passed_time":0.2415311911,"remaining_time":2.855022541},
{"learn":[5.558425806],"iteration":78,"passed_time":0.2424020923,"remaining_time":2.825978823},
{"learn":[5.541518902],"iteration":79,"passed_time":0.2436919226,"remaining_time":2.80245711},
{"learn":[5.526157283],"iteration":80,"passed_time":0.2444451706,"remaining_time":2.773396442},
{"learn":[5.511746977],"iteration":81,"passed_time":0.2451124418,"remaining_time":2.744063677},
{"learn":[5.504975022],"iteration":82,"passed_time":0.2454953536,"remaining_time":2.712279991},
{"learn":[5.493980522],"iteration":83,"passed_time":0.2462327503,"remaining_time":2.685109515},
{"learn":[5.480745463],"iteration":84,"passed_time":0.2469501299,"remaining_time":2.658345516},
{"learn":[5.464052013],"iteration":85,"passed_time":0.2476346076,"remaining_time":2.631837574},
{"learn":[5.449143727],"iteration":86,"passed_time":0.248479774,"remaining_time":2.607609582},
{"learn":[5.438255432],"iteration":87,"passed_time":0.2493457809,"remaining_time":2.584129002},
{"learn":[5.425927931],"iteration":88,"passed_time":0.2501632682,"remaining_time":2.56065997},
{"learn":[5.412331217],"iteration":89,"passed_time":0.2508281165,"remaining_time":2.536150956},
{"learn":[5.400691499],"iteration":90,"passed_time":0.2514480248,"remaining_time":2.511717083},
{"learn":[5.391618744],"iteration":91,"passed_time":0.2524038394,"remaining_time":2.491116154},
{"learn":[5.380766572],"iteration":92,"passed_time":0.2533708386,"remaining_time":2.471046781},
{"learn":[5.372207183],"iteration":93,"passed_time":0.2543671572,"remaining_time":2.45166643},
{"learn":[5.362918837],"iteration":94,"passed_time":0.2554663706,"remaining_time":2.43365332},
{"learn":[5.348292324],"iteration":95,"passed_time":0.2564810797,"remaining_time":2.415196834},
{"learn":[5.339772295],"iteration":96,"passed_time":0.2573596189,"remaining_time":2.395832328},
{"learn":[5.331515983],"iteration":97,"passed_time":0.2581438511,"remaining_time":2.375977079},
{"learn":[5.323861644],"iteration":98,"passed_time":0.2589184891,"remaining_time":2.356419784},
{"learn":[5.313277281],"iteration":99,"passed_time":0.2598280527,"remaining_time":2.338452474},
{"learn":[5.30685627],"iteration":100,"passed_time":0.2604885218,"remaining_time":2.318605754},
{"learn":[5.29652059],"iteration":101,"passed_time":0.261440063,"remaining_time":2.301697809},
{"learn":[5.288350766],"iteration":102,"passed_time":0.2623432766,"remaining_time":2.284678826},
{"learn":[5.27993346],"iteration":103,"passed_time":0.2630219331,"remaining_time":2.266035116},
{"learn":[5.271789139],"iteration":104,"passed_time":0.2636936992,"remaining_time":2.247674865},
{"learn":[5.262684686],"iteration":105,"passed_time":0.264471744,"remaining_time":2.230544708},
{"learn":[5.251619772],"iteration":106,"passed_time":0.2651472036,"remaining_time":2.212864045},
{"learn":[5.241012171],"iteration":107,"passed_time":0.2658393908,"remaining_time":2.19563645},
{"learn":[5.232684032],"iteration":108,"passed_time":0.2665967981,"remaining_time":2.179245386},
{"learn":[5.224267141],"iteration":109,"passed_time":0.2674174372,"remaining_time":2.163650173},
{"learn":[5.216324968],"iteration":110,"passed_time":0.2681453879,"remaining_time":2.147578827},
{"learn":[5.211102527],"iteration":111,"passed_time":0.2690058704,"remaining_time":2.132832258},
{"learn":[5.206364257],"iteration":112,"passed_time":0.2697502218,"remaining_time":2.117419883},
{"learn":[5.196937641],"iteration":113,"passed_time":0.2703725912,"remaining_time":2.101316805},
{"learn":[5.190746047],"iteration":114,"passed_time":0.2711797667,"remaining_time":2.086905161},
{"learn":[5.181885213],"iteration":115,"passed_time":0.2720449115,"remaining_time":2.073169843},
{"learn":[5.178293568],"iteration":116,"passed_time":0.2725472853,"remaining_time":2.056916692},
{"learn":[5.170991438],"iteration":117,"passed_time":0.2732566224,"remaining_time":2.042477466},
{"learn":[5.166257212],"iteration":118,"passed_time":0.2739450711,"remaining_time":2.02811435},
{"learn":[5.161421246],"iteration":119,"passed_time":0.2749262236,"remaining_time":2.01612564},
{"learn":[5.158223542],"iteration":120,"passed_time":0.2756236167,"remaining_time":2.002257513},
{"learn":[5.15470988],"iteration":121,"passed_time":0.2761673536,"remaining_time":1.987499479},
{"learn":[5.146388143],"iteration":122,"passed_time":0.2769313131,"remaining_time":1.974542777},
{"learn":[5.139529364],"iteration":123,"passed_time":0.2776693238,"remaining_time":1.961599416},
{"learn":[5.134276023],"iteration":124,"passed_time":0.2783659408,"remaining_time":1.948561586},
{"learn":[5.128536065],"iteration":125,"passed_time":0.2791522356,"remaining_time":1.936341698},
{"learn":[5.123300353],"iteration":126,"passed_time":0.2796699497,"remaining_time":1.922455638},
{"learn":[5.116200518],"iteration":127,"passed_time":0.2804163238,"remaining_time":1.910336206},
{"learn":[5.108728704],"iteration":128,"passed_time":0.281601615,"remaining_time":1.901356641},
{"learn":[5.104075866],"iteration":129,"passed_time":0.2822412332,"remaining_time":1.888845176},
{"learn":[5.100317606],"iteration":130,"passed_time":0.2828224015,"remaining_time":1.876127229},
{"learn":[5.095814182],"iteration":131,"passed_time":0.2833989696,"remaining_time":1.863562921},
{"learn":[5.092146915],"iteration":132,"passed_time":0.2839563948,"remaining_time":1.851054092},
{"learn":[5.085258329],"iteration":133,"passed_time":0.2845540937,"remaining_time":1.838983919},
{"learn":[5.079219421],"iteration":134,"passed_time":0.2852653337,"remaining_time":1.827811212},
{"learn":[5.076476829],"iteration":135,"passed_time":0.2858727794,"remaining_time":1.816132951},
{"learn":[5.072133867],"iteration":136,"passed_time":0.2865735745,"remaining_time":1.805204342},
{"learn":[5.067031564],"iteration":137,"passed_time":0.287337004,"remaining_time":1.794815199},
{"learn":[5.061358312],"iteration":138,"passed_time":0.2879992948,"remaining_time":1.783938078},
{"learn":[5.056759124],"iteration":139,"passed_time":0.2885783697,"remaining_time":1.772695699},
{"learn":[5.050254],"iteration":140,"passed_time":0.2892288412,"remaining_time":1.762039536},
{"learn":[5.048376474],"iteration":141,"passed_time":0.2896344141,"remaining_time":1.750044558},
{"learn":[5.042603751],"iteration":142,"passed_time":0.290266399,"remaining_time":1.739568559},
{"learn":[5.037477349],"iteration":143,"passed_time":0.2908771413,"remaining_time":1.729103007},
{"learn":[5.03230489],"iteration":144,"passed_time":0.2914646126,"remaining_time":1.718636164},
{"learn":[5.025976187],"iteration":145,"passed_time":0.2920347756,"remaining_time":1.708203413},
{"learn":[5.01952451],"iteration":146,"passed_time":0.2927923115,"remaining_time":1.69899212},
{"learn":[5.017569424],"iteration":147,"passed_time":0.2935140771,"remaining_time":1.689689147},
{"learn":[5.008962367],"iteration":148,"passed_time":0.2941904194,"remaining_time":1.680241925},
{"learn":[5.003880266],"iteration":149,"passed_time":0.2948450159,"remaining_time":1.670788423},
{"learn":[4.996387564],"iteration":150,"passed_time":0.295439575,"remaining_time":1.661113902},
{"learn":[4.993361683],"iteration":151,"passed_time":0.2960215895,"remaining_time":1.651488868},
{"learn":[4.99005752],"iteration":152,"passed_time":0.2965944419,"remaining_time":1.641931322},
{"learn":[4.986908764],"iteration":153,"passed_time":0.2971559969,"remaining_time":1.632428399},
{"learn":[4.985207175],"iteration":154,"passed_time":0.2977685657,"remaining_time":1.623318955},
{"learn":[4.979003494],"iteration":155,"passed_time":0.2983581827,"remaining_time":1.61419427},
{"learn":[4.973142217],"iteration":156,"passed_time":0.2989899839,"remaining_time":1.605404818},
{"learn":[4.967056696],"iteration":157,"passed_time":0.2997618162,"remaining_time":1.597464869},
{"learn":[4.961460696],"iteration":158,"passed_time":0.300709509,"remaining_time":1.590545264},
{"learn":[4.954240363],"iteration":159,"passed_time":0.301360804,"remaining_time":1.582144221},
{"learn":[4.952320707],"iteration":160,"passed_time":0.3017749028,"remaining_time":1.572603375},
{"learn":[4.948337777],"iteration":161,"passed_time":0.3023781864,"remaining_time":1.564153829},
{"learn":[4.943228639],"iteration":162,"passed_time":0.3031292907,"remaining_time":1.55655961},
{"learn":[4.938545759],"iteration":163,"passed_time":0.3038411886,"remaining_time":1.548848986},
{"learn":[4.935330572],"iteration":164,"passed_time":0.304469692,"remaining_time":1.540801168},
{"learn":[4.932051543],"iteration":165,"passed_time":0.305121098,"remaining_time":1.532957806},
{"learn":[4.928964153],"iteration":166,"passed_time":0.3058731964,"remaining_time":1.52570283},
{"learn":[4.922860227],"iteration":167,"passed_time":0.3066129037,"remaining_time":1.518463904},
{"learn":[4.917668772],"iteration":168,"passed_time":0.3073151541,"remaining_time":1.51111771},
{"learn":[4.910365386],"iteration":169,"passed_time":0.3079915784,"remaining_time":1.503723589},
{"learn":[4.906457206],"iteration":170,"passed_time":0.3086057356,"remaining_time":1.496106168},
{"learn":[4.901996508],"iteration":171,"passed_time":0.3092002135,"remaining_time":1.488475446},
{"learn":[4.896816173],"iteration":172,"passed_time":0.3098157547,"remaining_time":1.481026758},
{"learn":[4.891123132],"iteration":173,"passed_time":0.3107964914,"remaining_time":1.475390241},
{"learn":[4.887630202],"iteration":174,"passed_time":0.3115832333,"remaining_time":1.468892386},
{"learn":[4.885259712],"iteration":175,"passed_time":0.312363614,"remaining_time":1.462429647},
{"learn":[4.880659728],"iteration":176,"passed_time":0.3130298344,"remaining_time":1.455500303},
{"learn":[4.877299723],"iteration":177,"passed_time":0.3136998359,"remaining_time":1.448658793},
{"learn":[4.874038772],"iteration":178,"passed_time":0.3144115347,"remaining_time":1.442077486},
{"learn":[4.86943698],"iteration":179,"passed_time":0.3150190488,"remaining_time":1.435086778},
{"learn":[4.861268711],"iteration":180,"passed_time":0.3156773995,"remaining_time":1.428396631},
{"learn":[4.858673056],"iteration":181,"passed_time":0.3163241747,"remaining_time":1.421720741},
{"learn":[4.854036207],"iteration":182,"passed_time":0.3169507117,"remaining_time":1.415020391},
{"learn":[4.85130244],"iteration":183,"passed_time":0.3175527295,"remaining_time":1.408277322},
{"learn":[4.847510084],"iteration":184,"passed_time":0.3183292964,"remaining_time":1.402369603},
{"learn":[4.845691673],"iteration":185,"passed_time":0.3190269912,"remaining_time":1.396171886},
{"learn":[4.842058646],"iteration":186,"passed_time":0.3196759,"remaining_time":1.389820892},
{"learn":[4.838623675],"iteration":187,"passed_time":0.3203173864,"remaining_time":1.383498499},
{"learn":[4.834602161],"iteration":188,"passed_time":0.3209751015,"remaining_time":1.377305859},
{"learn":[4.830858976],"iteration":189,"passed_time":0.3215505194,"remaining_time":1.370820635},
{"learn":[4.827590511],"iteration":190,"passed_time":0.3221742343,"remaining_time":1.364601861},
{"learn":[4.822246226],"iteration":191,"passed_time":0.3227831863,"remaining_time":1.358379242},
{"learn":[4.816686395],"iteration":192,"passed_time":0.3233860944,"remaining_time":1.352189524},
{"learn":[4.814797121],"iteration":193,"passed_time":0.323992143,"remaining_time":1.34607045},
{"learn":[4.811639392],"iteration":194,"passed_time":0.3247158586,"remaining_time":1.340493673},
{"learn":[4.804813432],"iteration":195,"passed_time":0.3254437144,"remaining_time":1.3349834},
{"learn":[4.80251613],"iteration":196,"passed_time":0.3260561746,"remaining_time":1.32905131},
{"learn":[4.800087884],"iteration":197,"passed_time":0.3266595218,"remaining_time":1.323136043},
{"learn":[4.794773135],"iteration":198,"passed_time":0.3272623277,"remaining_time":1.317271982},
{"learn":[4.791664833],"iteration":199,"passed_time":0.3278435475,"remaining_time":1.31137419},
{"learn":[4.785989873],"iteration":200,"passed_time":0.3284300609,"remaining_time":1.305550342},
{"learn":[4.782387142],"iteration":201,"passed_time":0.3290814951,"remaining_time":1.300034817},
{"learn":[4.778623704],"iteration":202,"passed_time":0.3297896898,"remaining_time":1.294790063},
{"learn":[4.775772178],"iteration":203,"passed_time":0.3304399168,"remaining_time":1.289363597},
{"learn":[4.77023101],"iteration":204,"passed_time":0.331156653,"remaining_time":1.284241654},
{"learn":[4.764496689],"iteration":205,"passed_time":0.331981837,"remaining_time":1.279580478},
{"learn":[4.763138716],"iteration":206,"passed_time":0.3327903319,"remaining_time":1.274892431},
{"learn":[4.758053283],"iteration":207,"passed_time":0.3334022456,"remaining_time":1.269493166},
{"learn":[4.755063788],"iteration":208,"passed_time":0.3339903176,"remaining_time":1.26404948},
{"learn":[4.752465267],"iteration":209,"passed_time":0.3345851655,"remaining_time":1.258677527},
{"learn":[4.748067377],"iteration":210,"passed_time":0.3351695532,"remaining_time":1.253311742},
{"learn":[4.744163298],"iteration":211,"passed_time":0.3357788157,"remaining_time":1.248083523},
{"learn":[4.736670896],"iteration":212,"passed_time":0.3363882994,"remaining_time":1.242899491},
{"learn":[4.73349255],"iteration":213,"passed_time":0.3371309454,"remaining_time":1.238247304},
{"learn":[4.731864595],"iteration":214,"passed_time":0.3378296945,"remaining_time":1.23347121},
{"learn":[4.728398311],"iteration":215,"passed_time":0.3385270446,"remaining_time":1.228727792},
{"learn":[4.723865975],"iteration":216,"passed_time":0.3391968383,"remaining_time":1.223922232},
{"learn":[4.723483365],"iteration":217,"passed_time":0.3398691006,"remaining_time":1.219163471},
{"learn":[4.72095416],"iteration":218,"passed_time":0.3404512099,"remaining_time":1.214120525},
{"learn":[4.716173382],"iteration":219,"passed_time":0.3410281166,"remaining_time":1.209099686},
{"learn":[4.710563974],"iteration":220,"passed_time":0.3416355341,"remaining_time":1.204226611},
{"learn":[4.707160263],"iteration":221,"passed_time":0.3422402943,"remaining_time":1.199382653},
{"learn":[4.70408351],"iteration":222,"passed_time":0.3428080124,"remaining_time":1.194447649},
{"learn":[4.702501831],"iteration":223,"passed_time":0.3435146959,"remaining_time":1.190033054},
{"learn":[4.700269738],"iteration":224,"passed_time":0.3442122097,"remaining_time":1.185619833},
{"learn":[4.695346302],"iteration":225,"passed_time":0.3448857314,"remaining_time":1.181157328},
{"learn":[4.689769299],"iteration":226,"passed_time":0.345518889,"remaining_time":1.176590754},
{"learn":[4.687919514],"iteration":227,"passed_time":0.3461178145,"remaining_time":1.171942775},
{"learn":[4.682982074],"iteration":228,"passed_time":0.3468208044,"remaining_time":1.167680525},
{"learn":[4.679578702],"iteration":229,"passed_time":0.3474587497,"remaining_time":1.163231466},
{"learn":[4.675751423],"iteration":230,"passed_time":0.3481027277,"remaining_time":1.158835487},
{"learn":[4.672710726],"iteration":231,"passed_time":0.348760125,"remaining_time":1.154516276},
{"learn":[4.6690533],"iteration":232,"passed_time":0.3493545386,"remaining_time":1.150021164},
{"learn":[4.667595702],"iteration":233,"passed_time":0.3500447985,"remaining_time":1.145873144},
{"learn":[4.664241291],"iteration":234,"passed_time":0.3507487053,"remaining_time":1.141798977},
{"learn":[4.662246999],"iteration":235,"passed_time":0.3513737198,"remaining_time":1.137497974},
{"learn":[4.658668443],"iteration":236,"passed_time":0.3519795019,"remaining_time":1.133166076},
{"learn":[4.658017572],"iteration":237,"passed_time":0.3525741479,"remaining_time":1.128829835},
{"learn":[4.657656705],"iteration":238,"passed_time":0.3531587512,"remaining_time":1.124492927},
{"learn":[4.653242871],"iteration":239,"passed_time":0.353783621,"remaining_time":1.1203148},
{"learn":[4.6507302],"iteration":240,"passed_time":0.3543662474,"remaining_time":1.116033119},
{"learn":[4.647671336],"iteration":241,"passed_time":0.3549872214,"remaining_time":1.111902123},
{"learn":[4.645506007],"iteration":242,"passed_time":0.3556089811,"remaining_time":1.107802464},
{"learn":[4.641297906],"iteration":243,"passed_time":0.3563139652,"remaining_time":1.103989171},
{"learn":[4.63798107],"iteration":244,"passed_time":0.3570743297,"remaining_time":1.100371914},
{"learn":[4.635062318],"iteration":245,"passed_time":0.3578013989,"remaining_time":1.096675833},
{"learn":[4.631606017],"iteration":246,"passed_time":0.3583964455,"remaining_time":1.092601309},
{"learn":[4.630215494],"iteration":247,"passed_time":0.3589603843,"remaining_time":1.08846052},
{"learn":[4.62729814],"iteration":248,"passed_time":0.3595607727,"remaining_time":1.084458395},
{"learn":[4.624691756],"iteration":249,"passed_time":0.3601363056,"remaining_time":1.080408917},
{"learn":[4.621840053],"iteration":250,"passed_time":0.3607377697,"remaining_time":1.0764645},
{"learn":[4.619602091],"iteration":251,"passed_time":0.3613200784,"remaining_time":1.072489757},
{"learn":[4.613584029],"iteration":252,"passed_time":0.3618960795,"remaining_time":1.068523207},
{"learn":[4.6119388],"iteration":253,"passed_time":0.3625553065,"remaining_time":1.06482779},
{"learn":[4.60870702],"iteration":254,"passed_time":0.3634015518,"remaining_time":1.061702573},
{"learn":[4.604771557],"iteration":255,"passed_time":0.364116207,"remaining_time":1.058212727},
{"learn":[4.604231277],"iteration":256,"passed_time":0.3654460017,"remaining_time":1.056522877},
{"learn":[4.600750354],"iteration":257,"passed_time":0.3660760501,"remaining_time":1.052823369},
{"learn":[4.596488253],"iteration":258,"passed_time":0.3668715857,"remaining_time":1.049621023},
{"learn":[4.59470784],"iteration":259,"passed_time":0.3676031861,"remaining_time":1.046255222},
{"learn":[4.588818005],"iteration":260,"passed_time":0.3682039372,"remaining_time":1.042539117},
{"learn":[4.585054174],"iteration":261,"passed_time":0.3689104067,"remaining_time":1.039144581},
{"learn":[4.581471435],"iteration":262,"passed_time":0.3697433851,"remaining_time":1.036124999},
{"learn":[4.577555199],"iteration":263,"passed_time":0.3704774187,"remaining_time":1.032846137},
{"learn":[4.57457145],"iteration":264,"passed_time":0.371057692,"remaining_time":1.029160014},
{"learn":[4.573029224],"iteration":265,"passed_time":0.3716330584,"remaining_time":1.025483703},
{"learn":[4.571326203],"iteration":266,"passed_time":0.3722288899,"remaining_time":1.021886803},
{"learn":[4.571019224],"iteration":267,"passed_time":0.3728346145,"remaining_time":1.01833932},
{"learn":[4.565766631],"iteration":268,"passed_time":0.373439004,"remaining_time":1.014810081},
{"learn":[4.563383471],"iteration":269,"passed_time":0.3740721917,"remaining_time":1.01138037},
{"learn":[4.558165805],"iteration":270,"passed_time":0.3747475757,"remaining_time":1.008084807},
{"learn":[4.55629209],"iteration":271,"passed_time":0.3757871358,"remaining_time":1.005783216},
{"learn":[4.549383848],"iteration":272,"passed_time":0.3767372385,"remaining_time":1.003252646},
{"learn":[4.546227503],"iteration":273,"passed_time":0.3773245047,"remaining_time":0.9997722277},
{"learn":[4.540620977],"iteration":274,"passed_time":0.3779008539,"remaining_time":0.9962840695},
{"learn":[4.532898237],"iteration":275,"passed_time":0.3784710217,"remaining_time":0.9928007962},
{"learn":[4.529757367],"iteration":276,"passed_time":0.3790883026,"remaining_time":0.9894615263},
{"learn":[4.52579294],"iteration":277,"passed_time":0.3796938349,"remaining_time":0.9861113267},
{"learn":[4.521572155],"iteration":278,"passed_time":0.3803208529,"remaining_time":0.9828363259},
{"learn":[4.518818099],"iteration":279,"passed_time":0.380927902,"remaining_time":0.979528891},
{"learn":[4.514012334],"iteration":280,"passed_time":0.3816519618,"remaining_time":0.976540073},
{"learn":[4.508331416],"iteration":281,"passed_time":0.3825284767,"remaining_time":0.9739554832},
{"learn":[4.506038537],"iteration":282,"passed_time":0.3831523516,"remaining_time":0.9707428837},
{"learn":[4.505805643],"iteration":283,"passed_time":0.3837348466,"remaining_time":0.9674441906},
{"learn":[4.501550352],"iteration":284,"passed_time":0.3843289537,"remaining_time":0.9641936909},
{"learn":[4.494692643],"iteration":285,"passed_time":0.384948172,"remaining_time":0.9610244574},
{"learn":[4.489330245],"iteration":286,"passed_time":0.3855359963,"remaining_time":0.9577950014},
{"learn":[4.484826955],"iteration":287,"passed_time":0.3861487348,"remaining_time":0.9546454832},
{"learn":[4.478285428],"iteration":288,"passed_time":0.3867687018,"remaining_time":0.9515313045},
{"learn":[4.475311671],"iteration":289,"passed_time":0.3873658386,"remaining_time":0.9483784324},
{"learn":[4.471581298],"iteration":290,"passed_time":0.3881622299,"remaining_time":0.9457285946},
{"learn":[4.469164956],"iteration":291,"passed_time":0.388838536,"remaining_time":0.942800286},
{"learn":[4.462068024],"iteration":292,"passed_time":0.3895716327,"remaining_time":0.9400243834},
{"learn":[4.458540976],"iteration":293,"passed_time":0.3903572994,"remaining_time":0.9373886168},
{"learn":[4.455757458],"iteration":294,"passed_time":0.3910525894,"remaining_time":0.9345494086},
{"learn":[4.453027414],"iteration":295,"passed_time":0.3916986802,"remaining_time":0.9316076718},
{"learn":[4.450659338],"iteration":296,"passed_time":0.3923444903,"remaining_time":0.9286807295},
{"learn":[4.444696901],"iteration":297,"passed_time":0.3930332112,"remaining_time":0.925870182},
{"learn":[4.442052813],"iteration":298,"passed_time":0.393780595,"remaining_time":0.9232113616},
{"learn":[4.440036756],"iteration":299,"passed_time":0.3947305184,"remaining_time":0.9210378763},
{"learn":[4.435017051],"iteration":300,"passed_time":0.3954772806,"remaining_time":0.9184007279},
{"learn":[4.429962125],"iteration":301,"passed_time":0.396170899,"remaining_time":0.9156532698},
{"learn":[4.427666256],"iteration":302,"passed_time":0.3969600307,"remaining_time":0.9131390806},
{"learn":[4.425030004],"iteration":303,"passed_time":0.3976306821,"remaining_time":0.9103649827},
{"learn":[4.422588771],"iteration":304,"passed_time":0.3983359726,"remaining_time":0.9076836098},
{"learn":[4.418936667],"iteration":305,"passed_time":0.3990067837,"remaining_time":0.9049369538},
{"learn":[4.416887976],"iteration":306,"passed_time":0.3997094837,"remaining_time":0.9022758052},
{"learn":[4.413773354],"iteration":307,"passed_time":0.4007076248,"remaining_time":0.900291157},
{"learn":[4.411129391],"iteration":308,"passed_time":0.4014781268,"remaining_time":0.897803837},
{"learn":[4.40850819],"iteration":309,"passed_time":0.4023110107,"remaining_time":0.8954664431},
{"learn":[4.404880292],"iteration":310,"passed_time":0.4029599035,"remaining_time":0.8927311044},
{"learn":[4.404593827],"iteration":311,"passed_time":0.4035724843,"remaining_time":0.8899290679},
{"learn":[4.402139942],"iteration":312,"passed_time":0.4042406071,"remaining_time":0.88726293},
{"learn":[4.400284725],"iteration":313,"passed_time":0.4049008334,"remaining_time":0.8845922666},
{"learn":[4.395805521],"iteration":314,"passed_time":0.4056235263,"remaining_time":0.882070208},
{"learn":[4.392838833],"iteration":315,"passed_time":0.4062454449,"remaining_time":0.879341406},
{"learn":[4.389213061],"iteration":316,"passed_time":0.4070290462,"remaining_time":0.8769742541},
{"learn":[4.3861981],"iteration":317,"passed_time":0.4080034831,"remaining_time":0.8750263381},
{"learn":[4.385054234],"iteration":318,"passed_time":0.4088915809,"remaining_time":0.8729002087},
{"learn":[4.379364607],"iteration":319,"passed_time":0.4095510315,"remaining_time":0.8702959419},
{"learn":[4.378387619],"iteration":320,"passed_time":0.4101878082,"remaining_time":0.867655831},
{"learn":[4.375816727],"iteration":321,"passed_time":0.4108303265,"remaining_time":0.8650402526},
{"learn":[4.374600202],"iteration":322,"passed_time":0.4114949625,"remaining_time":0.8624832495},
{"learn":[4.37098897],"iteration":323,"passed_time":0.4122036831,"remaining_time":0.8600299067},
{"learn":[4.367418484],"iteration":324,"passed_time":0.4131774714,"remaining_time":0.8581378253},
{"learn":[4.363584638],"iteration":325,"passed_time":0.4144212266,"remaining_time":0.8568095298},
{"learn":[4.360770706],"iteration":326,"passed_time":0.4151875964,"remaining_time":0.8544992427},
{"learn":[4.358675808],"iteration":327,"passed_time":0.4157948924,"remaining_time":0.8518724626},
{"learn":[4.354228195],"iteration":328,"passed_time":0.4164143601,"remaining_time":0.849282783},
{"learn":[4.353773425],"iteration":329,"passed_time":0.4170720144,"remaining_time":0.8467825746},
{"learn":[4.351648009],"iteration":330,"passed_time":0.4176781008,"remaining_time":0.8441892733},
{"learn":[4.348209927],"iteration":331,"passed_time":0.4182737988,"remaining_time":0.8415870409},
{"learn":[4.345852733],"iteration":332,"passed_time":0.4188914343,"remaining_time":0.8390408009},
{"learn":[4.34237339],"iteration":333,"passed_time":0.4196124902,"remaining_time":0.8367123307},
{"learn":[4.340814362],"iteration":334,"passed_time":0.4203386418,"remaining_time":0.8344035725},
{"learn":[4.339707068],"iteration":335,"passed_time":0.4211112888,"remaining_time":0.8321961183},
{"learn":[4.335430786],"iteration":336,"passed_time":0.4218670875,"remaining_time":0.8299640327},
{"learn":[4.33521887],"iteration":337,"passed_time":0.422398615,"remaining_time":0.8273014295},
{"learn":[4.328507238],"iteration":338,"passed_time":0.4229812359,"remaining_time":0.8247510233},
{"learn":[4.326140732],"iteration":339,"passed_time":0.4235998148,"remaining_time":0.8222819934},
{"learn":[4.323785636],"iteration":340,"passed_time":0.4241974655,"remaining_time":0.8197833717},
{"learn":[4.320632534],"iteration":341,"passed_time":0.4248278902,"remaining_time":0.8173589233},
{"learn":[4.31973724],"iteration":342,"passed_time":0.4254602765,"remaining_time":0.8149486929},
{"learn":[4.318000924],"iteration":343,"passed_time":0.4261167807,"remaining_time":0.8125947912},
{"learn":[4.312713628],"iteration":344,"passed_time":0.4268927525,"remaining_time":0.8104775446},
{"learn":[4.308220789],"iteration":345,"passed_time":0.4276432022,"remaining_time":0.8083198099},
{"learn":[4.305890947],"iteration":346,"passed_time":0.4282905319,"remaining_time":0.8059761306},
{"learn":[4.305137856],"iteration":347,"passed_time":0.4290683715,"remaining_time":0.8038867191},
{"learn":[4.304787172],"iteration":348,"passed_time":0.4298003805,"remaining_time":0.8017193344},
{"learn":[4.30350134],"iteration":349,"passed_time":0.4304261965,"remaining_time":0.7993629363},
{"learn":[4.30293809],"iteration":350,"passed_time":0.4311343493,"remaining_time":0.7971686402},
{"learn":[4.299548459],"iteration":351,"passed_time":0.4317790837,"remaining_time":0.7948660405},
{"learn":[4.294768408],"iteration":352,"passed_time":0.4324972306,"remaining_time":0.7927073886},
{"learn":[4.294581479],"iteration":353,"passed_time":0.4334709566,"remaining_time":0.7910232711},
{"learn":[4.292551604],"iteration":354,"passed_time":0.4340697976,"remaining_time":0.7886620266},
{"learn":[4.288628894],"iteration":355,"passed_time":0.4348008527,"remaining_time":0.7865498571},
{"learn":[4.287802767],"iteration":356,"passed_time":0.435471827,"remaining_time":0.7843372122},
{"learn":[4.284566905],"iteration":357,"passed_time":0.436152059,"remaining_time":0.7821497819},
{"learn":[4.27890232],"iteration":358,"passed_time":0.4367551256,"remaining_time":0.7798329679},
{"learn":[4.276938023],"iteration":359,"passed_time":0.4373932333,"remaining_time":0.7775879703},
{"learn":[4.273425094],"iteration":360,"passed_time":0.4379926469,"remaining_time":0.7752833833},
{"learn":[4.269726505],"iteration":361,"passed_time":0.438669931,"remaining_time":0.7731254585},
{"learn":[4.265565857],"iteration":362,"passed_time":0.4394042361,"remaining_time":0.7710757531},
{"learn":[4.262117173],"iteration":363,"passed_time":0.4400830008,"remaining_time":0.7689362321},
{"learn":[4.259185148],"iteration":364,"passed_time":0.4408913779,"remaining_time":0.7670302053},
{"learn":[4.257668507],"iteration":365,"passed_time":0.4415708109,"remaining_time":0.7649068145},
{"learn":[4.253432436],"iteration":366,"passed_time":0.4421685886,"remaining_time":0.762650454},
{"learn":[4.250216667],"iteration":367,"passed_time":0.4427563712,"remaining_time":0.7603859418},
{"learn":[4.24514828],"iteration":368,"passed_time":0.4433484242,"remaining_time":0.7581378203},
{"learn":[4.244015772],"iteration":369,"passed_time":0.4439315727,"remaining_time":0.7558834886},
{"learn":[4.240329192],"iteration":370,"passed_time":0.4446333217,"remaining_time":0.7538392435},
{"learn":[4.236718014],"iteration":371,"passed_time":0.4454423514,"remaining_time":0.7519833244},
{"learn":[4.233495944],"iteration":372,"passed_time":0.4464071599,"remaining_time":0.7503948773},
{"learn":[4.230357491],"iteration":373,"passed_time":0.4474645063,"remaining_time":0.748964655},
{"learn":[4.227381215],"iteration":374,"passed_time":0.4481187876,"remaining_time":0.746864646},
{"learn":[4.226169067],"iteration":375,"passed_time":0.4488385301,"remaining_time":0.7448809648},
{"learn":[4.225963861],"iteration":376,"passed_time":0.4493960293,"remaining_time":0.7426358787},
{"learn":[4.224346548],"iteration":377,"passed_time":0.4499780992,"remaining_time":0.7404401527},
{"learn":[4.222595381],"iteration":378,"passed_time":0.4505695515,"remaining_time":0.7382683153},
{"learn":[4.219700938],"iteration":379,"passed_time":0.4512974251,"remaining_time":0.7363273777},
{"learn":[4.216356207],"iteration":380,"passed_time":0.4520562433,"remaining_time":0.734443083},
{"learn":[4.214326494],"iteration":381,"passed_time":0.4530359453,"remaining_time":0.7329220268},
{"learn":[4.212901398],"iteration":382,"passed_time":0.4540658137,"remaining_time":0.7314846138},
{"learn":[4.211331091],"iteration":383,"passed_time":0.4547842437,"remaining_time":0.7295497243},
{"learn":[4.208624791],"iteration":384,"passed_time":0.4553810282,"remaining_time":0.7274268373},
{"learn":[4.204659106],"iteration":385,"passed_time":0.4559843939,"remaining_time":0.7253223261},
{"learn":[4.202968852],"iteration":386,"passed_time":0.4565715137,"remaining_time":0.7231998396},
{"learn":[4.197261935],"iteration":387,"passed_time":0.4571826614,"remaining_time":0.7211231669},
{"learn":[4.196934403],"iteration":388,"passed_time":0.457823083,"remaining_time":0.7191000095},
{"learn":[4.192479929],"iteration":389,"passed_time":0.4585874795,"remaining_time":0.7172778526},
{"learn":[4.190243116],"iteration":390,"passed_time":0.4595763681,"remaining_time":0.7158107626},
{"learn":[4.185852431],"iteration":391,"passed_time":0.4605446348,"remaining_time":0.7143141275},
{"learn":[4.180967944],"iteration":392,"passed_time":0.4612340028,"remaining_time":0.712389414},
{"learn":[4.178283162],"iteration":393,"passed_time":0.4619695569,"remaining_time":0.7105420088},
{"learn":[4.176341157],"iteration":394,"passed_time":0.4627238513,"remaining_time":0.7087289368},
{"learn":[4.176041504],"iteration":395,"passed_time":0.4633708476,"remaining_time":0.7067575555},
{"learn":[4.175564513],"iteration":396,"passed_time":0.4643014549,"remaining_time":0.7052236204},
{"learn":[4.170830274],"iteration":397,"passed_time":0.4650180829,"remaining_time":0.7033690601},
{"learn":[4.167804808],"iteration":398,"passed_time":0.4658264902,"remaining_time":0.7016584476},
{"learn":[4.165860548],"iteration":399,"passed_time":0.466778836,"remaining_time":0.7001682539},
{"learn":[4.160950571],"iteration":400,"passed_time":0.467553225,"remaining_time":0.6984149171},
{"learn":[4.158544115],"iteration":401,"passed_time":0.4681660752,"remaining_time":0.6964261517},
{"learn":[4.154448767],"iteration":402,"passed_time":0.4687492333,"remaining_time":0.6944002289},
{"learn":[4.15197457],"iteration":403,"passed_time":0.4693399521,"remaining_time":0.6923926026},
{"learn":[4.149562679],"iteration":404,"passed_time":0.4699186224,"remaining_time":0.6903742725},
{"learn":[4.149327961],"iteration":405,"passed_time":0.4707366132,"remaining_time":0.6887131729},
{"learn":[4.147444889],"iteration":406,"passed_time":0.4716572967,"remaining_time":0.6872058402},
{"learn":[4.147254809],"iteration":407,"passed_time":0.4728089775,"remaining_time":0.6860365556},
{"learn":[4.144589165],"iteration":408,"passed_time":0.4734586307,"remaining_time":0.6841419334},
{"learn":[4.141691034],"iteration":409,"passed_time":0.4741467529,"remaining_time":0.6823087419},
{"learn":[4.138893468],"iteration":410,"passed_time":0.4747520295,"remaining_time":0.6803623974},
{"learn":[4.136964597],"iteration":411,"passed_time":0.4753579342,"remaining_time":0.6784234595},
{"learn":[4.133773523],"iteration":412,"passed_time":0.4760166083,"remaining_time":0.6765659783},
{"learn":[4.131363444],"iteration":413,"passed_time":0.4769659397,"remaining_time":0.6751257021},
{"learn":[4.130228592],"iteration":414,"passed_time":0.4778787115,"remaining_time":0.6736362559},
{"learn":[4.12884186],"iteration":415,"passed_time":0.4788313532,"remaining_time":0.6722055535},
{"learn":[4.12413494],"iteration":416,"passed_time":0.4798645219,"remaining_time":0.6708897272},
{"learn":[4.119422508],"iteration":417,"passed_time":0.4805646258,"remaining_time":0.6691115124},
{"learn":[4.117038244],"iteration":418,"passed_time":0.4812563393,"remaining_time":0.6673268094},
{"learn":[4.116067631],"iteration":419,"passed_time":0.4820311771,"remaining_time":0.6656621017},
{"learn":[4.110343455],"iteration":420,"passed_time":0.4837669038,"remaining_time":0.665323129},
{"learn":[4.105604544],"iteration":421,"passed_time":0.4849794085,"remaining_time":0.664260896},
{"learn":[4.103390131],"iteration":422,"passed_time":0.4862904727,"remaining_time":0.6633323941},
{"learn":[4.096724402],"iteration":423,"passed_time":0.4869985374,"remaining_time":0.6615829188},
{"learn":[4.093431279],"iteration":424,"passed_time":0.487657154,"remaining_time":0.6597714437},
{"learn":[4.091412744],"iteration":425,"passed_time":0.4884103269,"remaining_time":0.6580927879},
{"learn":[4.091192901],"iteration":426,"passed_time":0.4910761787,"remaining_time":0.6589851297},
{"learn":[4.088994581],"iteration":427,"passed_time":0.4922280179,"remaining_time":0.6578374445},
{"learn":[4.087845355],"iteration":428,"passed_time":0.492990508,"remaining_time":0.6561715153},
{"learn":[4.083650279],"iteration":429,"passed_time":0.4937288694,"remaining_time":0.6544778036},
{"learn":[4.079840652],"iteration":430,"passed_time":0.4944610352,"remaining_time":0.6527803457},
{"learn":[4.075707828],"iteration":431,"passed_time":0.4954089181,"remaining_time":0.651370985},
{"learn":[4.071345409],"iteration":432,"passed_time":0.4965705061,"remaining_time":0.6502435957},
{"learn":[4.067460475],"iteration":433,"passed_time":0.4978651289,"remaining_time":0.649289546},
{"learn":[4.064914749],"iteration":434,"passed_time":0.4985818382,"remaining_time":0.6475833071},
{"learn":[4.063823175],"iteration":435,"passed_time":0.4992680133,"remaining_time":0.6458421089},
{"learn":[4.058898471],"iteration":436,"passed_time":0.4999145624,"remaining_time":0.644054688},
{"learn":[4.054120355],"iteration":437,"passed_time":0.5006276244,"remaining_time":0.6423578195},
{"learn":[4.052715901],"iteration":438,"passed_time":0.5016395367,"remaining_time":0.6410473351},
{"learn":[4.052114167],"iteration":439,"passed_time":0.5027189945,"remaining_time":0.6398241748},
{"learn":[4.051377267],"iteration":440,"passed_time":0.5038183691,"remaining_time":0.6386269123},
{"learn":[4.049275336],"iteration":441,"passed_time":0.5047218924,"remaining_time":0.6371828415},
{"learn":[4.047099198],"iteration":442,"passed_time":0.5054818029,"remaining_time":0.6355606415},
{"learn":[4.044348685],"iteration":443,"passed_time":0.5063672566,"remaining_time":0.6340995376},
{"learn":[4.042822379],"iteration":444,"passed_time":0.5071999997,"remaining_time":0.6325752805},
{"learn":[4.041258611],"iteration":445,"passed_time":0.508218804,"remaining_time":0.6312852409},
{"learn":[4.040044254],"iteration":446,"passed_time":0.5099017139,"remaining_time":0.630818004},
{"learn":[4.036860137],"iteration":447,"passed_time":0.511275609,"remaining_time":0.6299645897},
{"learn":[4.036372284],"iteration":448,"passed_time":0.5120211568,"remaining_time":0.628337767},
{"learn":[4.03368231],"iteration":449,"passed_time":0.5126457443,"remaining_time":0.6265670208},
{"learn":[4.032439519],"iteration":450,"passed_time":0.513419699,"remaining_time":0.6249831812},
{"learn":[4.032008634],"iteration":451,"passed_time":0.514442535,"remaining_time":0.6237046663},
{"learn":[4.030034932],"iteration":452,"passed_time":0.5155831854,"remaining_time":0.6225695418},
{"learn":[4.028173412],"iteration":453,"passed_time":0.5169133674,"remaining_time":0.6216623318},
{"learn":[4.023806097],"iteration":454,"passed_time":0.5177256793,"remaining_time":0.6201329566},
{"learn":[4.020239186],"iteration":455,"passed_time":0.5184639615,"remaining_time":0.6185184102},
{"learn":[4.017384838],"iteration":456,"passed_time":0.5191504522,"remaining_time":0.6168461609},
{"learn":[4.016468229],"iteration":457,"passed_time":0.5204953114,"remaining_time":0.6159573336},
{"learn":[4.014530169],"iteration":458,"passed_time":0.5219004255,"remaining_time":0.6151375386},
{"learn":[4.012884822],"iteration":459,"passed_time":0.5229605129,"remaining_time":0.6139101673},
{"learn":[4.008924707],"iteration":460,"passed_time":0.523622108,"remaining_time":0.6122176057},
{"learn":[4.008286778],"iteration":461,"passed_time":0.5242841732,"remaining_time":0.6105300545},
{"learn":[4.006444202],"iteration":462,"passed_time":0.5249845703,"remaining_time":0.6088913914},
{"learn":[4.003284363],"iteration":463,"passed_time":0.5256475696,"remaining_time":0.6072135718},
{"learn":[3.999811484],"iteration":464,"passed_time":0.5265239309,"remaining_time":0.6057855979},
{"learn":[3.997483319],"iteration":465,"passed_time":0.5273363409,"remaining_time":0.6042867083},
{"learn":[3.99708333],"iteration":466,"passed_time":0.5290383671,"remaining_time":0.603806102},
{"learn":[3.995860263],"iteration":467,"passed_time":0.5298985336,"remaining_time":0.6023632903},
{"learn":[3.994131111],"iteration":468,"passed_time":0.5309975185,"remaining_time":0.6011933525},
{"learn":[3.993125499],"iteration":469,"passed_time":0.5316224169,"remaining_time":0.5994891084},
{"learn":[3.992954084],"iteration":470,"passed_time":0.5323859525,"remaining_time":0.5979451568},
{"learn":[3.990635743],"iteration":471,"passed_time":0.5335580604,"remaining_time":0.5968615591},
{"learn":[3.986678254],"iteration":472,"passed_time":0.5349251858,"remaining_time":0.5959948687},
{"learn":[3.986393291],"iteration":473,"passed_time":0.5364780896,"remaining_time":0.595332226},
{"learn":[3.986152671],"iteration":474,"passed_time":0.5371164756,"remaining_time":0.593655052},
{"learn":[3.985596662],"iteration":475,"passed_time":0.5378262941,"remaining_time":0.5920608783},
{"learn":[3.983853457],"iteration":476,"passed_time":0.5390305351,"remaining_time":0.5910125154},
{"learn":[3.983263928],"iteration":477,"passed_time":0.5401397176,"remaining_time":0.5898596916},
{"learn":[3.980067202],"iteration":478,"passed_time":0.5413715577,"remaining_time":0.5888404626},
{"learn":[3.978115407],"iteration":479,"passed_time":0.542046197,"remaining_time":0.5872167134},
{"learn":[3.972661644],"iteration":480,"passed_time":0.5431181455,"remaining_time":0.5860256081},
{"learn":[3.969938254],"iteration":481,"passed_time":0.5438666866,"remaining_time":0.584487435},
{"learn":[3.968211434],"iteration":482,"passed_time":0.5446813546,"remaining_time":0.5830233133},
{"learn":[3.966113368],"iteration":483,"passed_time":0.5456140529,"remaining_time":0.5816877093},
{"learn":[3.962246044],"iteration":484,"passed_time":0.5468495294,"remaining_time":0.5806752735},
{"learn":[3.961319703],"iteration":485,"passed_time":0.5475953052,"remaining_time":0.5791440059},
{"learn":[3.96078191],"iteration":486,"passed_time":0.5483868087,"remaining_time":0.5776641331},
{"learn":[3.958913633],"iteration":487,"passed_time":0.5492924909,"remaining_time":0.5763068757},
{"learn":[3.957428286],"iteration":488,"passed_time":0.5499329749,"remaining_time":0.5746743357},
{"learn":[3.952641965],"iteration":489,"passed_time":0.5506070459,"remaining_time":0.5730808029},
{"learn":[3.951486786],"iteration":490,"passed_time":0.5514415825,"remaining_time":0.5716573635},
{"learn":[3.94938344],"iteration":491,"passed_time":0.552434042,"remaining_time":0.5703993767},
{"learn":[3.947297924],"iteration":492,"passed_time":0.5533062223,"remaining_time":0.5690187723},
{"learn":[3.946284886],"iteration":493,"passed_time":0.553948316,"remaining_time":0.5674045504},
{"learn":[3.943288204],"iteration":494,"passed_time":0.5547139604,"remaining_time":0.565920303},
{"learn":[3.943076488],"iteration":495,"passed_time":0.5557035164,"remaining_time":0.5646664764},
{"learn":[3.942347078],"iteration":496,"passed_time":0.5564395527,"remaining_time":0.5631571328},
{"learn":[3.940251541],"iteration":497,"passed_time":0.5571828453,"remaining_time":0.5616582095},
{"learn":[3.939011019],"iteration":498,"passed_time":0.5581757471,"remaining_time":0.5604129244},
{"learn":[3.938760512],"iteration":499,"passed_time":0.5605931692,"remaining_time":0.5605931692},
{"learn":[3.934522727],"iteration":500,"passed_time":0.5614837814,"remaining_time":0.5592423292},
{"learn":[3.930091193],"iteration":501,"passed_time":0.5622556093,"remaining_time":0.5577754849},
{"learn":[3.927671752],"iteration":502,"passed_time":0.5630343159,"remaining_time":0.5563182008},
{"learn":[3.927280041],"iteration":503,"passed_time":0.5639741455,"remaining_time":0.555022175},
{"learn":[3.925987561],"iteration":504,"passed_time":0.5648761371,"remaining_time":0.553690471},
{"learn":[3.921645957],"iteration":505,"passed_time":0.5658250741,"remaining_time":0.5524062976},
{"learn":[3.920333743],"iteration":506,"passed_time":0.5664956812,"remaining_time":0.5508528025},
{"learn":[3.918659461],"iteration":507,"passed_time":0.5674431959,"remaining_time":0.5495709692},
{"learn":[3.916124385],"iteration":508,"passed_time":0.5681477107,"remaining_time":0.5480560431},
{"learn":[3.913849268],"iteration":509,"passed_time":0.5688032072,"remaining_time":0.5464971991},
{"learn":[3.912826119],"iteration":510,"passed_time":0.5698347311,"remaining_time":0.545301729},
{"learn":[3.910034145],"iteration":511,"passed_time":0.5708257393,"remaining_time":0.5440682828},
{"learn":[3.90792379],"iteration":512,"passed_time":0.5720494862,"remaining_time":0.5430567248},
{"learn":[3.907823851],"iteration":513,"passed_time":0.5728625493,"remaining_time":0.5416560291},
{"learn":[3.904527401],"iteration":514,"passed_time":0.5738232054,"remaining_time":0.5403966109},
{"learn":[3.903378283],"iteration":515,"passed_time":0.574503047,"remaining_time":0.5388749511},
{"learn":[3.902170135],"iteration":516,"passed_time":0.5752836492,"remaining_time":0.537450682},
{"learn":[3.899435429],"iteration":517,"passed_time":0.5765241769,"remaining_time":0.5364568596},
{"learn":[3.897497505],"iteration":518,"passed_time":0.5778804669,"remaining_time":0.535569373},
{"learn":[3.896426119],"iteration":519,"passed_time":0.5785721704,"remaining_time":0.5340666189},
{"learn":[3.896044669],"iteration":520,"passed_time":0.5792549407,"remaining_time":0.532558765},
{"learn":[3.892795942],"iteration":521,"passed_time":0.5800874264,"remaining_time":0.5311911683},
{"learn":[3.892413888],"iteration":522,"passed_time":0.5807209049,"remaining_time":0.529644114},
{"learn":[3.891738985],"iteration":523,"passed_time":0.5814021117,"remaining_time":0.528143903},
{"learn":[3.88822057],"iteration":524,"passed_time":0.5824113446,"remaining_time":0.5269435975},
{"learn":[3.883837053],"iteration":525,"passed_time":0.583643223,"remaining_time":0.5259446534},
{"learn":[3.881769742],"iteration":526,"passed_time":0.5845060732,"remaining_time":0.5246136103},
{"learn":[3.880356898],"iteration":527,"passed_time":0.5853206776,"remaining_time":0.5232412118},
{"learn":[3.879250273],"iteration":528,"passed_time":0.5862576276,"remaining_time":0.5219798537},
{"learn":[3.877174493],"iteration":529,"passed_time":0.5870836604,"remaining_time":0.5206213592},
{"learn":[3.875854201],"iteration":530,"passed_time":0.5880023479,"remaining_time":0.5193467065},
{"learn":[3.873189396],"iteration":531,"passed_time":0.5889566504,"remaining_time":0.5181047225},
{"learn":[3.871583368],"iteration":532,"passed_time":0.5900272453,"remaining_time":0.5169657102},
{"learn":[3.869622679],"iteration":533,"passed_time":0.5908068201,"remaining_time":0.5155729928},
{"learn":[3.866860164],"iteration":534,"passed_time":0.5918282865,"remaining_time":0.5143928098},
{"learn":[3.864498444],"iteration":535,"passed_time":0.5928781587,"remaining_time":0.513237809},
{"learn":[3.861416322],"iteration":536,"passed_time":0.5935833732,"remaining_time":0.5117860368},
{"learn":[3.860265769],"iteration":537,"passed_time":0.5945590057,"remaining_time":0.5105692576},
{"learn":[3.859328725],"iteration":538,"passed_time":0.5951681049,"remaining_time":0.5090398819},
{"learn":[3.858521278],"iteration":539,"passed_time":0.5957564503,"remaining_time":0.5074962355},
{"learn":[3.85599111],"iteration":540,"passed_time":0.5964014385,"remaining_time":0.5060041779},
{"learn":[3.852379816],"iteration":541,"passed_time":0.5970285063,"remaining_time":0.5045001031},
{"learn":[3.851327537],"iteration":542,"passed_time":0.5976377655,"remaining_time":0.5029842704},
{"learn":[3.847854898],"iteration":543,"passed_time":0.5982488947,"remaining_time":0.5014733382},
{"learn":[3.847083414],"iteration":544,"passed_time":0.5988159243,"remaining_time":0.4999288909},
{"learn":[3.845397429],"iteration":545,"passed_time":0.599386265,"remaining_time":0.4983907771},
{"learn":[3.841933528],"iteration":546,"passed_time":0.5999751179,"remaining_time":0.4968715328},
{"learn":[3.840996474],"iteration":547,"passed_time":0.6009239218,"remaining_time":0.4956525778},
{"learn":[3.838355966],"iteration":548,"passed_time":0.6018578651,"remaining_time":0.4944223992},
{"learn":[3.83342799],"iteration":549,"passed_time":0.603148529,"remaining_time":0.4934851601},
{"learn":[3.828161535],"iteration":550,"passed_time":0.6041136374,"remaining_time":0.4922813488},
{"learn":[3.823502399],"iteration":551,"passed_time":0.6047774704,"remaining_time":0.490833889},
{"learn":[3.820068862],"iteration":552,"passed_time":0.6053976096,"remaining_time":0.4893539448},
{"learn":[3.817951642],"iteration":553,"passed_time":0.6060242692,"remaining_time":0.4878823539},
{"learn":[3.815785958],"iteration":554,"passed_time":0.6069999009,"remaining_time":0.4866936142},
{"learn":[3.81503012],"iteration":555,"passed_time":0.608050523,"remaining_time":0.4855655256},
{"learn":[3.813529315],"iteration":556,"passed_time":0.6093184611,"remaining_time":0.4846105535},
{"learn":[3.808881326],"iteration":557,"passed_time":0.6104393749,"remaining_time":0.4835379994},
{"learn":[3.808740434],"iteration":558,"passed_time":0.6111942004,"remaining_time":0.4821764622},
{"learn":[3.80714352],"iteration":559,"passed_time":0.6118387579,"remaining_time":0.4807304526},
{"learn":[3.80573346],"iteration":560,"passed_time":0.6124938137,"remaining_time":0.4792955155},
{"learn":[3.803370052],"iteration":561,"passed_time":0.6132709685,"remaining_time":0.4779585128},
{"learn":[3.803215211],"iteration":562,"passed_time":0.6140520179,"remaining_time":0.4766265219},
{"learn":[3.801309667],"iteration":563,"passed_time":0.615571906,"remaining_time":0.4758676436},
{"learn":[3.800003847],"iteration":564,"passed_time":0.6163164154,"remaining_time":0.4745090986},
{"learn":[3.798026138],"iteration":565,"passed_time":0.6170231564,"remaining_time":0.4731237631},
{"learn":[3.794745847],"iteration":566,"passed_time":0.6177533333,"remaining_time":0.4717587184},
{"learn":[3.794312041],"iteration":567,"passed_time":0.6184413714,"remaining_time":0.47036386},
{"learn":[3.792205926],"iteration":568,"passed_time":0.6191505963,"remaining_time":0.4689875343},
{"learn":[3.788991061],"iteration":569,"passed_time":0.6204657421,"remaining_time":0.4680706475},
{"learn":[3.787391572],"iteration":570,"passed_time":0.6215764177,"remaining_time":0.4669987446},
{"learn":[3.7826445],"iteration":571,"passed_time":0.6222715452,"remaining_time":0.4656157716},
{"learn":[3.781700331],"iteration":572,"passed_time":0.623096576,"remaining_time":0.4643320034},
{"learn":[3.780045374],"iteration":573,"passed_time":0.6237739417,"remaining_time":0.4629402424},
{"learn":[3.775462644],"iteration":574,"passed_time":0.6244778823,"remaining_time":0.4615706086},
{"learn":[3.773711943],"iteration":575,"passed_time":0.6251182733,"remaining_time":0.4601565067},
{"learn":[3.772415806],"iteration":576,"passed_time":0.6258892897,"remaining_time":0.4588408484},
{"learn":[3.770170875],"iteration":577,"passed_time":0.627114658,"remaining_time":0.4578587987},
{"learn":[3.765166479],"iteration":578,"passed_time":0.6279753014,"remaining_time":0.4566107114},
{"learn":[3.763976102],"iteration":579,"passed_time":0.6289501939,"remaining_time":0.4554466922},
{"learn":[3.760761708],"iteration":580,"passed_time":0.6296327334,"remaining_time":0.4540724876},
{"learn":[3.758155662],"iteration":581,"passed_time":0.6303564332,"remaining_time":0.4527302218},
{"learn":[3.756844548],"iteration":582,"passed_time":0.6310068907,"remaining_time":0.4513376902},
{"learn":[3.753098923],"iteration":583,"passed_time":0.6318538718,"remaining_time":0.4500876895},
{"learn":[3.751618946],"iteration":584,"passed_time":0.6328534614,"remaining_time":0.4489473273},
{"learn":[3.751398464],"iteration":585,"passed_time":0.6338907582,"remaining_time":0.4478340852},
{"learn":[3.749920103],"iteration":586,"passed_time":0.6346216219,"remaining_time":0.4465055023},
{"learn":[3.748237465],"iteration":587,"passed_time":0.6355705589,"remaining_time":0.4453317522},
{"learn":[3.746021536],"iteration":588,"passed_time":0.6362461621,"remaining_time":0.443968035},
{"learn":[3.74417648],"iteration":589,"passed_time":0.6369779016,"remaining_time":0.4426456605},
{"learn":[3.738788389],"iteration":590,"passed_time":0.6377745837,"remaining_time":0.441370228},
{"learn":[3.736021611],"iteration":591,"passed_time":0.6387206032,"remaining_time":0.4401993347},
{"learn":[3.734546151],"iteration":592,"passed_time":0.6399505341,"remaining_time":0.4392240596},
{"learn":[3.733527479],"iteration":593,"passed_time":0.6406896325,"remaining_time":0.4379124424},
{"learn":[3.733026392],"iteration":594,"passed_time":0.6415086181,"remaining_time":0.4366571266},
{"learn":[3.730314752],"iteration":595,"passed_time":0.6421807762,"remaining_time":0.4353037476},
{"learn":[3.727342596],"iteration":596,"passed_time":0.6430122189,"remaining_time":0.4340601745},
{"learn":[3.725459604],"iteration":597,"passed_time":0.6436169333,"remaining_time":0.4326655638},
{"learn":[3.723158842],"iteration":598,"passed_time":0.6443738186,"remaining_time":0.4313754612},
{"learn":[3.722362756],"iteration":599,"passed_time":0.6455382551,"remaining_time":0.4303588368},
{"learn":[3.721443615],"iteration":600,"passed_time":0.6467164444,"remaining_time":0.4293508508},
{"learn":[3.720743486],"iteration":601,"passed_time":0.6474705358,"remaining_time":0.4280619157},
{"learn":[3.720215334],"iteration":602,"passed_time":0.6483092786,"remaining_time":0.4268304869},
{"learn":[3.719436563],"iteration":603,"passed_time":0.6489665146,"remaining_time":0.4254813573},
{"learn":[3.715046574],"iteration":604,"passed_time":0.6497347009,"remaining_time":0.4242069535},
{"learn":[3.71443396],"iteration":605,"passed_time":0.6505433498,"remaining_time":0.4229605278},
{"learn":[3.712938941],"iteration":606,"passed_time":0.6514005968,"remaining_time":0.4217470092},
{"learn":[3.712814764],"iteration":607,"passed_time":0.6525144408,"remaining_time":0.4207001},
{"learn":[3.71235348],"iteration":608,"passed_time":0.6532705218,"remaining_time":0.4194232743},
{"learn":[3.711223749],"iteration":609,"passed_time":0.654172601,"remaining_time":0.418241499},
{"learn":[3.710755648],"iteration":610,"passed_time":0.6548555611,"remaining_time":0.4169211346},
{"learn":[3.708668039],"iteration":611,"passed_time":0.6556516834,"remaining_time":0.4156745967},
{"learn":[3.705623591],"iteration":612,"passed_time":0.6562844091,"remaining_time":0.4143263725},
{"learn":[3.704045802],"iteration":613,"passed_time":0.6574859491,"remaining_time":0.4133380722},
{"learn":[3.699915209],"iteration":614,"passed_time":0.6588032848,"remaining_time":0.4124215685},
{"learn":[3.696182221],"iteration":615,"passed_time":0.6595554197,"remaining_time":0.4111514305},
{"learn":[3.694263278],"iteration":616,"passed_time":0.6607027306,"remaining_time":0.4101282752},
{"learn":[3.693810229],"iteration":617,"passed_time":0.6613675371,"remaining_time":0.4088064711},
{"learn":[3.690900932],"iteration":618,"passed_time":0.6619917659,"remaining_time":0.4074618139},
{"learn":[3.688020895],"iteration":619,"passed_time":0.6626177198,"remaining_time":0.4061205379},
{"learn":[3.685491894],"iteration":620,"passed_time":0.6634603339,"remaining_time":0.4049137947},
{"learn":[3.684328128],"iteration":621,"passed_time":0.6641956097,"remaining_time":0.4036429911},
{"learn":[3.680640153],"iteration":622,"passed_time":0.6654804391,"remaining_time":0.4027064616},
{"learn":[3.678932783],"iteration":623,"passed_time":0.6661818459,"remaining_time":0.4014172661},
{"learn":[3.674167041],"iteration":624,"passed_time":0.6669045553,"remaining_time":0.4001427332},
{"learn":[3.672200976],"iteration":625,"passed_time":0.6675482579,"remaining_time":0.3988227611},
{"learn":[3.670606604],"iteration":626,"passed_time":0.6683020042,"remaining_time":0.3975704108},
{"learn":[3.665506042],"iteration":627,"passed_time":0.6688920048,"remaining_time":0.3962226525},
{"learn":[3.664214007],"iteration":628,"passed_time":0.6697395694,"remaining_time":0.3950292214},
{"learn":[3.66261643],"iteration":629,"passed_time":0.6705399873,"remaining_time":0.3938091989},
{"learn":[3.662118449],"iteration":630,"passed_time":0.6714273262,"remaining_time":0.3926413365},
{"learn":[3.660871366],"iteration":631,"passed_time":0.6724540298,"remaining_time":0.391555511},
{"learn":[3.656695243],"iteration":632,"passed_time":0.6731111232,"remaining_time":0.3902555801},
{"learn":[3.654497801],"iteration":633,"passed_time":0.6737192709,"remaining_time":0.3889294214},
{"learn":[3.654189134],"iteration":634,"passed_time":0.6743477679,"remaining_time":0.3876172209},
{"learn":[3.653957699],"iteration":635,"passed_time":0.6748932926,"remaining_time":0.3862596832},
{"learn":[3.651920725],"iteration":636,"passed_time":0.6756540552,"remaining_time":0.3850273501},
{"learn":[3.65106705],"iteration":637,"passed_time":0.6765314117,"remaining_time":0.3838626505},
{"learn":[3.650612844],"iteration":638,"passed_time":0.6774487685,"remaining_time":0.3827214483},
{"learn":[3.649884732],"iteration":639,"passed_time":0.6781024723,"remaining_time":0.3814326407},
{"learn":[3.646276182],"iteration":640,"passed_time":0.6788042736,"remaining_time":0.3801727523},
{"learn":[3.645808194],"iteration":641,"passed_time":0.6793545772,"remaining_time":0.3788301225},
{"learn":[3.645042989],"iteration":642,"passed_time":0.6800065551,"remaining_time":0.3775464077},
{"learn":[3.639864499],"iteration":643,"passed_time":0.6806252426,"remaining_time":0.3762462521},
{"learn":[3.637318478],"iteration":644,"passed_time":0.6812730231,"remaining_time":0.374964222},
{"learn":[3.636344905],"iteration":645,"passed_time":0.6820437994,"remaining_time":0.3737515557},
{"learn":[3.634754643],"iteration":646,"passed_time":0.6828150027,"remaining_time":0.3725404884},
{"learn":[3.630724975],"iteration":647,"passed_time":0.683806074,"remaining_time":0.3714502131},
{"learn":[3.629408252],"iteration":648,"passed_time":0.6845090141,"remaining_time":0.3702044129},
{"learn":[3.62790646],"iteration":649,"passed_time":0.6854668288,"remaining_time":0.3690975232},
{"learn":[3.627388973],"iteration":650,"passed_time":0.6862221691,"remaining_time":0.3678825454},
{"learn":[3.625163557],"iteration":651,"passed_time":0.6870195742,"remaining_time":0.3666914292},
{"learn":[3.623701985],"iteration":652,"passed_time":0.6876144478,"remaining_time":0.3653938949},
{"learn":[3.622342639],"iteration":653,"passed_time":0.6883318089,"remaining_time":0.3641633118},
{"learn":[3.621130639],"iteration":654,"passed_time":0.6892538489,"remaining_time":0.3630421036},
{"learn":[3.619125665],"iteration":655,"passed_time":0.6900232021,"remaining_time":0.3618414352},
{"learn":[3.618878783],"iteration":656,"passed_time":0.691041065,"remaining_time":0.3607718193},
{"learn":[3.616207429],"iteration":657,"passed_time":0.6917163493,"remaining_time":0.3595243031},
{"learn":[3.61206486],"iteration":658,"passed_time":0.6923310598,"remaining_time":0.3582471797},
{"learn":[3.611955873],"iteration":659,"passed_time":0.6929542792,"remaining_time":0.3569764469},
{"learn":[3.610713743],"iteration":660,"passed_time":0.6936661345,"remaining_time":0.355753131},
{"learn":[3.610044025],"iteration":661,"passed_time":0.694453137,"remaining_time":0.3545697285},
{"learn":[3.607342669],"iteration":662,"passed_time":0.6951964778,"remaining_time":0.3533653289},
{"learn":[3.602510618],"iteration":663,"passed_time":0.6959459391,"remaining_time":0.3521654149},
{"learn":[3.600492392],"iteration":664,"passed_time":0.6966300488,"remaining_time":0.3509339344},
{"learn":[3.597171065],"iteration":665,"passed_time":0.697420066,"remaining_time":0.3497572103},
{"learn":[3.594358798],"iteration":666,"passed_time":0.6980235717,"remaining_time":0.3484885298},
{"learn":[3.593945251],"iteration":667,"passed_time":0.6986192793,"remaining_time":0.3472179652},
{"learn":[3.593607748],"iteration":668,"passed_time":0.6993588366,"remaining_time":0.3460205903},
{"learn":[3.592238714],"iteration":669,"passed_time":0.6999926814,"remaining_time":0.3447725147},
{"learn":[3.590144654],"iteration":670,"passed_time":0.7008567219,"remaining_time":0.3436391379},
{"learn":[3.587151536],"iteration":671,"passed_time":0.7016102639,"remaining_time":0.3424526288},
{"learn":[3.586070865],"iteration":672,"passed_time":0.7023586487,"remaining_time":0.3412649006},
{"learn":[3.585102746],"iteration":673,"passed_time":0.7030165056,"remaining_time":0.3400346897},
{"learn":[3.584362847],"iteration":674,"passed_time":0.7036260287,"remaining_time":0.3387829027},
{"learn":[3.581407561],"iteration":675,"passed_time":0.7042531045,"remaining_time":0.3375414288},
{"learn":[3.57919422],"iteration":676,"passed_time":0.7048616174,"remaining_time":0.3362929135},
{"learn":[3.577632204],"iteration":677,"passed_time":0.7058547146,"remaining_time":0.3352289353},
{"learn":[3.573911195],"iteration":678,"passed_time":0.7066370456,"remaining_time":0.3340655252},
{"learn":[3.573408216],"iteration":679,"passed_time":0.7073776134,"remaining_time":0.3328835828},
{"learn":[3.571076482],"iteration":680,"passed_time":0.7080472306,"remaining_time":0.3316697012},
{"learn":[3.568177107],"iteration":681,"passed_time":0.7087473711,"remaining_time":0.3304716481},
{"learn":[3.564824621],"iteration":682,"passed_time":0.7095530422,"remaining_time":0.3293240328},
{"learn":[3.562475026],"iteration":683,"passed_time":0.7101659279,"remaining_time":0.3280883526},
{"learn":[3.561226889],"iteration":684,"passed_time":0.7107602988,"remaining_time":0.3268459768},
{"learn":[3.559383467],"iteration":685,"passed_time":0.7113883832,"remaining_time":0.3256209217},
{"learn":[3.555209766],"iteration":686,"passed_time":0.7123985213,"remaining_time":0.3245716698},
{"learn":[3.55345383],"iteration":687,"passed_time":0.7145008782,"remaining_time":0.3240178401},
{"learn":[3.552300968],"iteration":688,"passed_time":0.7152319566,"remaining_time":0.3228405494},
{"learn":[3.551253986],"iteration":689,"passed_time":0.7159120375,"remaining_time":0.32164164},
{"learn":[3.549807725],"iteration":690,"passed_time":0.7166062671,"remaining_time":0.3204505594},
{"learn":[3.547992926],"iteration":691,"passed_time":0.7171661469,"remaining_time":0.3192011174},
{"learn":[3.545438607],"iteration":692,"passed_time":0.7177480126,"remaining_time":0.3179634053},
{"learn":[3.543313763],"iteration":693,"passed_time":0.7187789751,"remaining_time":0.3169256},
{"learn":[3.542962896],"iteration":694,"passed_time":0.7198170558,"remaining_time":0.3158909381},
{"learn":[3.539800465],"iteration":695,"passed_time":0.720726654,"remaining_time":0.3148001477},
{"learn":[3.53953187],"iteration":696,"passed_time":0.7214429229,"remaining_time":0.3136258331},
{"learn":[3.536332425],"iteration":697,"passed_time":0.722083256,"remaining_time":0.3124199761},
{"learn":[3.534993327],"iteration":698,"passed_time":0.7226765726,"remaining_time":0.3111954912},
{"learn":[3.531637011],"iteration":699,"passed_time":0.7233394939,"remaining_time":0.3100026403},
{"learn":[3.531040284],"iteration":700,"passed_time":0.7239619256,"remaining_time":0.308794031},
{"learn":[3.529973872],"iteration":701,"passed_time":0.7246745557,"remaining_time":0.3076253812},
{"learn":[3.527325183],"iteration":702,"passed_time":0.7254998362,"remaining_time":0.3065056207},
{"learn":[3.527200815],"iteration":703,"passed_time":0.7265191146,"remaining_time":0.3054682641},
{"learn":[3.523459911],"iteration":704,"passed_time":0.7273475871,"remaining_time":0.304351118},
{"learn":[3.522729934],"iteration":705,"passed_time":0.728007667,"remaining_time":0.3031646659},
{"learn":[3.522260582],"iteration":706,"passed_time":0.7286979563,"remaining_time":0.3019922223},
{"learn":[3.518641591],"iteration":707,"passed_time":0.729303569,"remaining_time":0.3007862177},
{"learn":[3.516856405],"iteration":708,"passed_time":0.7299926446,"remaining_time":0.299616163},
{"learn":[3.515083413],"iteration":709,"passed_time":0.7306052986,"remaining_time":0.2984162487},
{"learn":[3.514671214],"iteration":710,"passed_time":0.7311842907,"remaining_time":0.2972043038},
{"learn":[3.512617621],"iteration":711,"passed_time":0.7317652837,"remaining_time":0.2959949462},
{"learn":[3.510747971],"iteration":712,"passed_time":0.7324587955,"remaining_time":0.2948326428},
{"learn":[3.508149266],"iteration":713,"passed_time":0.7332554382,"remaining_time":0.2937129626},
{"learn":[3.504557165],"iteration":714,"passed_time":0.7339273084,"remaining_time":0.2925444516},
{"learn":[3.501367208],"iteration":715,"passed_time":0.7345534296,"remaining_time":0.2913591816},
{"learn":[3.497593362],"iteration":716,"passed_time":0.7352652776,"remaining_time":0.2902093076},
{"learn":[3.496291169],"iteration":717,"passed_time":0.7359346639,"remaining_time":0.2890439766},
{"learn":[3.49330374],"iteration":718,"passed_time":0.7365892914,"remaining_time":0.2878742571},
{"learn":[3.490044385],"iteration":719,"passed_time":0.7373775751,"remaining_time":0.2867579459},
{"learn":[3.488891789],"iteration":720,"passed_time":0.7380014235,"remaining_time":0.2855789142},
{"learn":[3.486869081],"iteration":721,"passed_time":0.7386412776,"remaining_time":0.2844075834},
{"learn":[3.486303638],"iteration":722,"passed_time":0.7392902541,"remaining_time":0.2832412177},
{"learn":[3.486035862],"iteration":723,"passed_time":0.7401492206,"remaining_time":0.2821563327},
{"learn":[3.482668951],"iteration":724,"passed_time":0.7407755046,"remaining_time":0.2809838121},
{"learn":[3.47820549],"iteration":725,"passed_time":0.7416853618,"remaining_time":0.2799198197},
{"learn":[3.474392283],"iteration":726,"passed_time":0.7423110157,"remaining_time":0.2787495286},
{"learn":[3.472268163],"iteration":727,"passed_time":0.7430501323,"remaining_time":0.2776231263},
{"learn":[3.471209164],"iteration":728,"passed_time":0.7437177713,"remaining_time":0.2764712154},
{"learn":[3.470049971],"iteration":729,"passed_time":0.7444135351,"remaining_time":0.2753310335},
{"learn":[3.469078654],"iteration":730,"passed_time":0.7454217173,"remaining_time":0.2743070341},
{"learn":[3.468643292],"iteration":731,"passed_time":0.7463573961,"remaining_time":0.273256533},
{"learn":[3.468134848],"iteration":732,"passed_time":0.7470342137,"remaining_time":0.2721120533},
{"learn":[3.467820182],"iteration":733,"passed_time":0.7476188347,"remaining_time":0.270935436},
{"learn":[3.465776156],"iteration":734,"passed_time":0.7482325391,"remaining_time":0.2697709154},
{"learn":[3.463037608],"iteration":735,"passed_time":0.7488202476,"remaining_time":0.2685985671},
{"learn":[3.45965637],"iteration":736,"passed_time":0.7494298181,"remaining_time":0.2674356067},
{"learn":[3.457275091],"iteration":737,"passed_time":0.7500125209,"remaining_time":0.2662646077},
{"learn":[3.455522955],"iteration":738,"passed_time":0.7506583222,"remaining_time":0.2651174859},
{"learn":[3.451270508],"iteration":739,"passed_time":0.7515574691,"remaining_time":0.2640607324},
{"learn":[3.450978947],"iteration":740,"passed_time":0.7523420367,"remaining_time":0.2629643556},
{"learn":[3.450608492],"iteration":741,"passed_time":0.7530815566,"remaining_time":0.2618531558},
{"learn":[3.448122004],"iteration":742,"passed_time":0.7537057436,"remaining_time":0.2607030634},
{"learn":[3.445646714],"iteration":743,"passed_time":0.7543273421,"remaining_time":0.259553494},
{"learn":[3.44411263],"iteration":744,"passed_time":0.7549845793,"remaining_time":0.2584175406},
{"learn":[3.443264164],"iteration":745,"passed_time":0.7557647003,"remaining_time":0.2573247103},
{"learn":[3.439521363],"iteration":746,"passed_time":0.7564364193,"remaining_time":0.2561960028},
{"learn":[3.436809225],"iteration":747,"passed_time":0.7571340907,"remaining_time":0.2550772605},
{"learn":[3.435509465],"iteration":748,"passed_time":0.7578039849,"remaining_time":0.2539503341},
{"learn":[3.434450277],"iteration":749,"passed_time":0.758702289,"remaining_time":0.252900763},
{"learn":[3.431786753],"iteration":750,"passed_time":0.7595390952,"remaining_time":0.2518312047},
{"learn":[3.430150302],"iteration":751,"passed_time":0.760188867,"remaining_time":0.2507005838},
{"learn":[3.42696281],"iteration":752,"passed_time":0.7609195365,"remaining_time":0.2495977762},
{"learn":[3.426870334],"iteration":753,"passed_time":0.7615135234,"remaining_time":0.2484513618},
{"learn":[3.425200309],"iteration":754,"passed_time":0.762117785,"remaining_time":0.2473097448},
{"learn":[3.423383783],"iteration":755,"passed_time":0.7627209384,"remaining_time":0.2461691918},
{"learn":[3.422752979],"iteration":756,"passed_time":0.7633539191,"remaining_time":0.2450396332},
{"learn":[3.420845924],"iteration":757,"passed_time":0.7640471551,"remaining_time":0.2439306221},
{"learn":[3.418917862],"iteration":758,"passed_time":0.7648308625,"remaining_time":0.2428514333},
{"learn":[3.417095735],"iteration":759,"passed_time":0.7655995397,"remaining_time":0.2417682757},
{"learn":[3.414391848],"iteration":760,"passed_time":0.7663141021,"remaining_time":0.2406689493},
{"learn":[3.41426711],"iteration":761,"passed_time":0.7669898987,"remaining_time":0.2395585248},
{"learn":[3.411976013],"iteration":762,"passed_time":0.767602124,"remaining_time":0.2384294933},
{"learn":[3.408614844],"iteration":763,"passed_time":0.7682297363,"remaining_time":0.2373065678},
{"learn":[3.407906721],"iteration":764,"passed_time":0.7688923456,"remaining_time":0.2361956879},
{"learn":[3.407494015],"iteration":765,"passed_time":0.7696560718,"remaining_time":0.2351168679},
{"learn":[3.406287128],"iteration":766,"passed_time":0.7705493019,"remaining_time":0.2340782103},
{"learn":[3.404600442],"iteration":767,"passed_time":0.7713877708,"remaining_time":0.2330233891},
{"learn":[3.404012662],"iteration":768,"passed_time":0.7724023709,"remaining_time":0.2320220386},
{"learn":[3.400398762],"iteration":769,"passed_time":0.7731644774,"remaining_time":0.2309452335},
{"learn":[3.399737714],"iteration":770,"passed_time":0.7741094116,"remaining_time":0.2299235477},
{"learn":[3.399185251],"iteration":771,"passed_time":0.7748493151,"remaining_time":0.2288415076},
{"learn":[3.397245411],"iteration":772,"passed_time":0.7755007799,"remaining_time":0.2277343817},
{"learn":[3.396229831],"iteration":773,"passed_time":0.7763833415,"remaining_time":0.2266959111},
{"learn":[3.394002836],"iteration":774,"passed_time":0.7774802785,"remaining_time":0.2257200809},
{"learn":[3.389617243],"iteration":775,"passed_time":0.7782645164,"remaining_time":0.2246536748},
{"learn":[3.385426488],"iteration":776,"passed_time":0.7790457628,"remaining_time":0.2235871366},
{"learn":[3.385072258],"iteration":777,"passed_time":0.7796808908,"remaining_time":0.2224796372},
{"learn":[3.383842366],"iteration":778,"passed_time":0.7802791431,"remaining_time":0.2213628891},
{"learn":[3.380110746],"iteration":779,"passed_time":0.7808775433,"remaining_time":0.2202475122},
{"learn":[3.378595218],"iteration":780,"passed_time":0.7814780089,"remaining_time":0.2191340383},
{"learn":[3.377371219],"iteration":781,"passed_time":0.7820834383,"remaining_time":0.2180232603},
{"learn":[3.375814782],"iteration":782,"passed_time":0.7827792652,"remaining_time":0.2169388257},
{"learn":[3.374195887],"iteration":783,"passed_time":0.7836185127,"remaining_time":0.2158948964},
{"learn":[3.373704309],"iteration":784,"passed_time":0.784425535,"remaining_time":0.2148426625},
{"learn":[3.372971757],"iteration":785,"passed_time":0.7852431694,"remaining_time":0.2137939418},
{"learn":[3.371565136],"iteration":786,"passed_time":0.7858397919,"remaining_time":0.212685992},
{"learn":[3.3700309],"iteration":787,"passed_time":0.7864513014,"remaining_time":0.2115833451},
{"learn":[3.368186663],"iteration":788,"passed_time":0.7870478977,"remaining_time":0.2104779549},
{"learn":[3.366710398],"iteration":789,"passed_time":0.7876297794,"remaining_time":0.2093699414},
{"learn":[3.364598042],"iteration":790,"passed_time":0.7882337435,"remaining_time":0.2082690928},
{"learn":[3.36348442],"iteration":791,"passed_time":0.7888389252,"remaining_time":0.2071698187},
{"learn":[3.362001759],"iteration":792,"passed_time":0.7895063471,"remaining_time":0.2060880376},
{"learn":[3.361580401],"iteration":793,"passed_time":0.7902969185,"remaining_time":0.2050392509},
{"learn":[3.359543675],"iteration":794,"passed_time":0.7910864467,"remaining_time":0.2039908448},
{"learn":[3.35766119],"iteration":795,"passed_time":0.7922778989,"remaining_time":0.2030460947},
{"learn":[3.354592969],"iteration":796,"passed_time":0.792916823,"remaining_time":0.2019599938},
{"learn":[3.350985986],"iteration":797,"passed_time":0.793503679,"remaining_time":0.2008618335},
{"learn":[3.349589624],"iteration":798,"passed_time":0.7940968412,"remaining_time":0.1997665395},
{"learn":[3.349110856],"iteration":799,"passed_time":0.7946866954,"remaining_time":0.1986716739},
{"learn":[3.345315441],"iteration":800,"passed_time":0.7953260932,"remaining_time":0.1975903777},
{"learn":[3.34397474],"iteration":801,"passed_time":0.7961445749,"remaining_time":0.1965543963},
{"learn":[3.343800902],"iteration":802,"passed_time":0.7970293728,"remaining_time":0.195535226},
{"learn":[3.342329465],"iteration":803,"passed_time":0.7978045267,"remaining_time":0.1944896607},
{"learn":[3.34220347],"iteration":804,"passed_time":0.798494682,"remaining_time":0.1934241776},
{"learn":[3.341279219],"iteration":805,"passed_time":0.7991305145,"remaining_time":0.1923465506},
{"learn":[3.337329521],"iteration":806,"passed_time":0.7997420787,"remaining_time":0.1912642146},
{"learn":[3.336708453],"iteration":807,"passed_time":0.8003389509,"remaining_time":0.1901795527},
{"learn":[3.333252703],"iteration":808,"passed_time":0.8009933814,"remaining_time":0.1891096858},
{"learn":[3.332186769],"iteration":809,"passed_time":0.8016488175,"remaining_time":0.1880410807},
{"learn":[3.330594851],"iteration":810,"passed_time":0.8024642628,"remaining_time":0.1870107838},
{"learn":[3.327867442],"iteration":811,"passed_time":0.8031716102,"remaining_time":0.1859559886},
{"learn":[3.327563111],"iteration":812,"passed_time":0.8039172078,"remaining_time":0.1849108461},
{"learn":[3.326308994],"iteration":813,"passed_time":0.8046194441,"remaining_time":0.1838565315},
{"learn":[3.326249879],"iteration":814,"passed_time":0.8052070747,"remaining_time":0.182777066},
{"learn":[3.322336238],"iteration":815,"passed_time":0.8058501961,"remaining_time":0.1817113187},
{"learn":[3.320491154],"iteration":816,"passed_time":0.8065730841,"remaining_time":0.1806644729},
{"learn":[3.320434271],"iteration":817,"passed_time":0.807117396,"remaining_time":0.1795786871},
{"learn":[3.319609638],"iteration":818,"passed_time":0.8077368785,"remaining_time":0.1785108364},
{"learn":[3.316182682],"iteration":819,"passed_time":0.8088529112,"remaining_time":0.1775530781},
{"learn":[3.313126612],"iteration":820,"passed_time":0.8099064797,"remaining_time":0.1765813153},
{"learn":[3.311222803],"iteration":821,"passed_time":0.8107474555,"remaining_time":0.1755633176},
{"learn":[3.309627335],"iteration":822,"passed_time":0.811462689,"remaining_time":0.1745187071},
{"learn":[3.307974895],"iteration":823,"passed_time":0.8120941106,"remaining_time":0.1734569945},
{"learn":[3.307321505],"iteration":824,"passed_time":0.8126865175,"remaining_time":0.1723880492},
{"learn":[3.306759087],"iteration":825,"passed_time":0.8133072784,"remaining_time":0.1713262306},
{"learn":[3.30484037],"iteration":826,"passed_time":0.8140706138,"remaining_time":0.1702953037},
{"learn":[3.30201994],"iteration":827,"passed_time":0.8153834525,"remaining_time":0.1693791713},
{"learn":[3.299302297],"iteration":828,"passed_time":0.8166200192,"remaining_time":0.168446349},
{"learn":[3.298132671],"iteration":829,"passed_time":0.8174084726,"remaining_time":0.1674210125},
{"learn":[3.296976183],"iteration":830,"passed_time":0.8180559776,"remaining_time":0.1663675815},
{"learn":[3.293144745],"iteration":831,"passed_time":0.819006285,"remaining_time":0.1653762691},
{"learn":[3.290284404],"iteration":832,"passed_time":0.8196665129,"remaining_time":0.1643268999},
{"learn":[3.288285745],"iteration":833,"passed_time":0.8202590847,"remaining_time":0.1632649977},
{"learn":[3.286662667],"iteration":834,"passed_time":0.8208849992,"remaining_time":0.1622108082},
{"learn":[3.285692682],"iteration":835,"passed_time":0.8215545649,"remaining_time":0.1611662065},
{"learn":[3.284565611],"iteration":836,"passed_time":0.8227379875,"remaining_time":0.160222571},
{"learn":[3.283897383],"iteration":837,"passed_time":0.8235977675,"remaining_time":0.1592157975},
{"learn":[3.280712855],"iteration":838,"passed_time":0.8243070821,"remaining_time":0.1581805009},
{"learn":[3.280468341],"iteration":839,"passed_time":0.8249378498,"remaining_time":0.157131019},
{"learn":[3.277814895],"iteration":840,"passed_time":0.825661758,"remaining_time":0.1561001421},
{"learn":[3.276316385],"iteration":841,"passed_time":0.8264867545,"remaining_time":0.1550889634},
{"learn":[3.27557063],"iteration":842,"passed_time":0.8270835833,"remaining_time":0.1540357326},
{"learn":[3.27499628],"iteration":843,"passed_time":0.8281039764,"remaining_time":0.1530618724},
{"learn":[3.273569958],"iteration":844,"passed_time":0.8288239079,"remaining_time":0.1520327878},
{"learn":[3.269665595],"iteration":845,"passed_time":0.8296297094,"remaining_time":0.1510200653},
{"learn":[3.267984685],"iteration":846,"passed_time":0.8307008013,"remaining_time":0.1500557528},
{"learn":[3.267702508],"iteration":847,"passed_time":0.8313832088,"remaining_time":0.1490215186},
{"learn":[3.266671924],"iteration":848,"passed_time":0.8322607648,"remaining_time":0.1480228215},
{"learn":[3.265359825],"iteration":849,"passed_time":0.83290875,"remaining_time":0.1469838971},
{"learn":[3.2618983],"iteration":850,"passed_time":0.8336646151,"remaining_time":0.1459647798},
{"learn":[3.260456253],"iteration":851,"passed_time":0.834539269,"remaining_time":0.1449669153},
{"learn":[3.258389147],"iteration":852,"passed_time":0.8354807726,"remaining_time":0.14398086},
{"learn":[3.258108469],"iteration":853,"passed_time":0.836317081,"remaining_time":0.1429769248},
{"learn":[3.256424936],"iteration":854,"passed_time":0.837179558,"remaining_time":0.1419778198},
{"learn":[3.254817983],"iteration":855,"passed_time":0.8381408358,"remaining_time":0.1409956546},
{"learn":[3.253898449],"iteration":856,"passed_time":0.8388227616,"remaining_time":0.1399669252},
{"learn":[3.253023652],"iteration":857,"passed_time":0.8396672593,"remaining_time":0.13896591},
{"learn":[3.252845542],"iteration":858,"passed_time":0.8410393609,"remaining_time":0.1380518625},
{"learn":[3.252316026],"iteration":859,"passed_time":0.8425695092,"remaining_time":0.1371624782},
{"learn":[3.24975301],"iteration":860,"passed_time":0.8434483689,"remaining_time":0.1361664614},
{"learn":[3.249151075],"iteration":861,"passed_time":0.8440760524,"remaining_time":0.1351305049},
{"learn":[3.246257135],"iteration":862,"passed_time":0.8447964455,"remaining_time":0.1341102121},
{"learn":[3.243826471],"iteration":863,"passed_time":0.8455248273,"remaining_time":0.133091871},
{"learn":[3.243190653],"iteration":864,"passed_time":0.8466132046,"remaining_time":0.1321303845},
{"learn":[3.24008797],"iteration":865,"passed_time":0.8475527154,"remaining_time":0.1311455703},
{"learn":[3.240036811],"iteration":866,"passed_time":0.8486849023,"remaining_time":0.1301904175},
{"learn":[3.238676314],"iteration":867,"passed_time":0.8502647385,"remaining_time":0.1293029326},
{"learn":[3.237848782],"iteration":868,"passed_time":0.8510065187,"remaining_time":0.1282875189},
{"learn":[3.236405498],"iteration":869,"passed_time":0.8517162149,"remaining_time":0.1272679402},
{"learn":[3.233378068],"iteration":870,"passed_time":0.852784282,"remaining_time":0.1263021497},
{"learn":[3.233169169],"iteration":871,"passed_time":0.8541414925,"remaining_time":0.1253785677},
{"learn":[3.232434885],"iteration":872,"passed_time":0.855402597,"remaining_time":0.1244400112},
{"learn":[3.229978115],"iteration":873,"passed_time":0.8565372851,"remaining_time":0.1234824919},
{"learn":[3.229648848],"iteration":874,"passed_time":0.857287434,"remaining_time":0.1224696334},
{"learn":[3.227208761],"iteration":875,"passed_time":0.858201836,"remaining_time":0.1214806252},
{"learn":[3.226258869],"iteration":876,"passed_time":0.8592663563,"remaining_time":0.1205128413},
{"learn":[3.225331995],"iteration":877,"passed_time":0.8603471206,"remaining_time":0.1195470942},
{"learn":[3.221968268],"iteration":878,"passed_time":0.8611379139,"remaining_time":0.118541169},
{"learn":[3.221166317],"iteration":879,"passed_time":0.8621144082,"remaining_time":0.1175610557},
{"learn":[3.220047503],"iteration":880,"passed_time":0.8627520768,"remaining_time":0.116535184},
{"learn":[3.21982781],"iteration":881,"passed_time":0.8634613592,"remaining_time":0.1155197737},
{"learn":[3.216693405],"iteration":882,"passed_time":0.8641739696,"remaining_time":0.1145054977},
{"learn":[3.214798761],"iteration":883,"passed_time":0.8649397636,"remaining_time":0.113498883},
{"learn":[3.214395085],"iteration":884,"passed_time":0.8657524845,"remaining_time":0.1124989104},
{"learn":[3.213470696],"iteration":885,"passed_time":0.8669140032,"remaining_time":0.1115442397},
{"learn":[3.211595017],"iteration":886,"passed_time":0.8677721973,"remaining_time":0.1105504603},
{"learn":[3.210965255],"iteration":887,"passed_time":0.8686972878,"remaining_time":0.1095654237},
{"learn":[3.209413583],"iteration":888,"passed_time":0.8693227008,"remaining_time":0.1085431044},
{"learn":[3.208331683],"iteration":889,"passed_time":0.8700404383,"remaining_time":0.1075330879},
{"learn":[3.207110711],"iteration":890,"passed_time":0.8709672873,"remaining_time":0.106549309},
{"learn":[3.204519413],"iteration":891,"passed_time":0.8717482692,"remaining_time":0.1055479967},
{"learn":[3.201421296],"iteration":892,"passed_time":0.8729264384,"remaining_time":0.1045947692},
{"learn":[3.200691259],"iteration":893,"passed_time":0.8737170648,"remaining_time":0.1035950882},
{"learn":[3.200485067],"iteration":894,"passed_time":0.8745479517,"remaining_time":0.1026005977},
{"learn":[3.197467568],"iteration":895,"passed_time":0.8751581668,"remaining_time":0.1015808586},
{"learn":[3.195838544],"iteration":896,"passed_time":0.8758393012,"remaining_time":0.1005701762},
{"learn":[3.195671746],"iteration":897,"passed_time":0.8766396233,"remaining_time":0.09957376568},
{"learn":[3.194213094],"iteration":898,"passed_time":0.8775215915,"remaining_time":0.09858696411},
{"learn":[3.192884691],"iteration":899,"passed_time":0.8785059038,"remaining_time":0.09761176709},
{"learn":[3.188364239],"iteration":900,"passed_time":0.8796878297,"remaining_time":0.0966582632},
{"learn":[3.185219478],"iteration":901,"passed_time":0.8804174975,"remaining_time":0.09565511614},
{"learn":[3.184120387],"iteration":902,"passed_time":0.8814581602,"remaining_time":0.09468598177},
{"learn":[3.183725321],"iteration":903,"passed_time":0.8821873711,"remaining_time":0.09368361463},
{"learn":[3.181264554],"iteration":904,"passed_time":0.8828877943,"remaining_time":0.09267882924},
{"learn":[3.180741589],"iteration":905,"passed_time":0.8841341805,"remaining_time":0.09173136089},
{"learn":[3.179782639],"iteration":906,"passed_time":0.885402851,"remaining_time":0.09078551835},
{"learn":[3.176377564],"iteration":907,"passed_time":0.8861700504,"remaining_time":0.08978815488},
{"learn":[3.174078182],"iteration":908,"passed_time":0.8871001566,"remaining_time":0.08880760643},
{"learn":[3.171242379],"iteration":909,"passed_time":0.8877285365,"remaining_time":0.08779732779},
{"learn":[3.170421012],"iteration":910,"passed_time":0.8883551756,"remaining_time":0.08678771749},
{"learn":[3.170087224],"iteration":911,"passed_time":0.8890117277,"remaining_time":0.08578183337},
{"learn":[3.167303059],"iteration":912,"passed_time":0.8898622247,"remaining_time":0.08479519556},
{"learn":[3.16705966],"iteration":913,"passed_time":0.8906464609,"remaining_time":0.08380262105},
{"learn":[3.165667683],"iteration":914,"passed_time":0.8916891861,"remaining_time":0.08283451455},
{"learn":[3.164689733],"iteration":915,"passed_time":0.8923728869,"remaining_time":0.0818333215},
{"learn":[3.163311455],"iteration":916,"passed_time":0.893332154,"remaining_time":0.08085776312},
{"learn":[3.159425016],"iteration":917,"passed_time":0.893971058,"remaining_time":0.07985362392},
{"learn":[3.159327058],"iteration":918,"passed_time":0.8946100348,"remaining_time":0.07885028598},
{"learn":[3.15819426],"iteration":919,"passed_time":0.8952663291,"remaining_time":0.07784924601},
{"learn":[3.157086603],"iteration":920,"passed_time":0.8963897862,"remaining_time":0.07688902618},
{"learn":[3.153354154],"iteration":921,"passed_time":0.8973182264,"remaining_time":0.07591195408},
{"learn":[3.153261317],"iteration":922,"passed_time":0.8980364449,"remaining_time":0.0749174499},
{"learn":[3.153168454],"iteration":923,"passed_time":0.8987991972,"remaining_time":0.07392720669},
{"learn":[3.152080399],"iteration":924,"passed_time":0.8994948845,"remaining_time":0.07293201766},
{"learn":[3.151635144],"iteration":925,"passed_time":0.9000981022,"remaining_time":0.07193008592},
{"learn":[3.147762655],"iteration":926,"passed_time":0.9007405988,"remaining_time":0.07093210756},
{"learn":[3.147172317],"iteration":927,"passed_time":0.9013262621,"remaining_time":0.06993048585},
{"learn":[3.146254125],"iteration":928,"passed_time":0.9020463046,"remaining_time":0.06894002974},
{"learn":[3.144869828],"iteration":929,"passed_time":0.9029244891,"remaining_time":0.06796205832},
{"learn":[3.143466218],"iteration":930,"passed_time":0.9040297521,"remaining_time":0.06700113093},
{"learn":[3.141919643],"iteration":931,"passed_time":0.9047412318,"remaining_time":0.06601116283},
{"learn":[3.141054135],"iteration":932,"passed_time":0.9055114017,"remaining_time":0.06502600634},
{"learn":[3.139390417],"iteration":933,"passed_time":0.9061274239,"remaining_time":0.06403041753},
{"learn":[3.139025283],"iteration":934,"passed_time":0.9067285441,"remaining_time":0.06303460467},
{"learn":[3.137824183],"iteration":935,"passed_time":0.9073186396,"remaining_time":0.06203888134},
{"learn":[3.135620453],"iteration":936,"passed_time":0.9079356832,"remaining_time":0.06104583569},
{"learn":[3.13443178],"iteration":937,"passed_time":0.9089112329,"remaining_time":0.06007728831},
{"learn":[3.132765713],"iteration":938,"passed_time":0.9095959784,"remaining_time":0.05908983459},
{"learn":[3.131434124],"iteration":939,"passed_time":0.9104247593,"remaining_time":0.05811221868},
{"learn":[3.128384262],"iteration":940,"passed_time":0.9110626705,"remaining_time":0.05712295171},
{"learn":[3.128120455],"iteration":941,"passed_time":0.91175673,"remaining_time":0.05613788783},
{"learn":[3.126314615],"iteration":942,"passed_time":0.9123652204,"remaining_time":0.05514826889},
{"learn":[3.125409666],"iteration":943,"passed_time":0.9129632072,"remaining_time":0.05415883433},
{"learn":[3.123072589],"iteration":944,"passed_time":0.9135610767,"remaining_time":0.05317022139},
{"learn":[3.122921099],"iteration":945,"passed_time":0.9141377855,"remaining_time":0.05218122665},
{"learn":[3.122182662],"iteration":946,"passed_time":0.9148439184,"remaining_time":0.05120034602},
{"learn":[3.120040951],"iteration":947,"passed_time":0.915631966,"remaining_time":0.05022453822},
{"learn":[3.118767799],"iteration":948,"passed_time":0.9163204947,"remaining_time":0.04924377791},
{"learn":[3.118203218],"iteration":949,"passed_time":0.9169613378,"remaining_time":0.04826112304},
{"learn":[3.116343362],"iteration":950,"passed_time":0.9177841781,"remaining_time":0.04728856438},
{"learn":[3.11480829],"iteration":951,"passed_time":0.9184690008,"remaining_time":0.04630936139},
{"learn":[3.112607903],"iteration":952,"passed_time":0.9190889952,"remaining_time":0.04532757899},
{"learn":[3.111661241],"iteration":953,"passed_time":0.9197220909,"remaining_time":0.04434718677},
{"learn":[3.110249676],"iteration":954,"passed_time":0.9203302194,"remaining_time":0.04336634542},
{"learn":[3.107333579],"iteration":955,"passed_time":0.9210323689,"remaining_time":0.04239061112},
{"learn":[3.107149851],"iteration":956,"passed_time":0.9217729407,"remaining_time":0.04141717497},
{"learn":[3.106867336],"iteration":957,"passed_time":0.9224354973,"remaining_time":0.04044080468},
{"learn":[3.10364681],"iteration":958,"passed_time":0.9234877549,"remaining_time":0.03948174969},
{"learn":[3.102703811],"iteration":959,"passed_time":0.9242733684,"remaining_time":0.03851139035},
{"learn":[3.101469264],"iteration":960,"passed_time":0.9249465255,"remaining_time":0.03753685171},
{"learn":[3.09863569],"iteration":961,"passed_time":0.9256911001,"remaining_time":0.03656576071},
{"learn":[3.09645939],"iteration":962,"passed_time":0.926296478,"remaining_time":0.03558979199},
{"learn":[3.096240186],"iteration":963,"passed_time":0.9269312083,"remaining_time":0.03461568828},
{"learn":[3.094838828],"iteration":964,"passed_time":0.9277161704,"remaining_time":0.03364773675},
{"learn":[3.094176802],"iteration":965,"passed_time":0.9285218243,"remaining_time":0.03268089237},
{"learn":[3.093182279],"iteration":966,"passed_time":0.9291808506,"remaining_time":0.03170937753},
{"learn":[3.090150687],"iteration":967,"passed_time":0.9298600545,"remaining_time":0.03073917535},
{"learn":[3.088612829],"iteration":968,"passed_time":0.9304859858,"remaining_time":0.02976786952},
{"learn":[3.087153684],"iteration":969,"passed_time":0.9311040114,"remaining_time":0.02879703128},
{"learn":[3.085866843],"iteration":970,"passed_time":0.9317156746,"remaining_time":0.02782672973},
{"learn":[3.082669094],"iteration":971,"passed_time":0.9323345873,"remaining_time":0.02685737494},
{"learn":[3.081047548],"iteration":972,"passed_time":0.9330106388,"remaining_time":0.02589032605},
{"learn":[3.079684322],"iteration":973,"passed_time":0.9337347155,"remaining_time":0.02492515668},
{"learn":[3.07613431],"iteration":974,"passed_time":0.9344790946,"remaining_time":0.02396100243},
{"learn":[3.074005935],"iteration":975,"passed_time":0.9352207337,"remaining_time":0.02299723116},
{"learn":[3.072988853],"iteration":976,"passed_time":0.9362106979,"remaining_time":0.02203976055},
{"learn":[3.072344268],"iteration":977,"passed_time":0.9370998509,"remaining_time":0.02107995575},
{"learn":[3.070654438],"iteration":978,"passed_time":0.9377736368,"remaining_time":0.02011567556},
{"learn":[3.069724506],"iteration":979,"passed_time":0.9384302898,"remaining_time":0.01915163857},
{"learn":[3.067763166],"iteration":980,"passed_time":0.9390698199,"remaining_time":0.01818789661},
{"learn":[3.066737893],"iteration":981,"passed_time":0.9397261041,"remaining_time":0.01722512207},
{"learn":[3.065248174],"iteration":982,"passed_time":0.9404446097,"remaining_time":0.01626404717},
{"learn":[3.063186837],"iteration":983,"passed_time":0.9413251234,"remaining_time":0.01530609957},
{"learn":[3.062880371],"iteration":984,"passed_time":0.9419908125,"remaining_time":0.01434503775},
{"learn":[3.061288645],"iteration":985,"passed_time":0.9426735056,"remaining_time":0.01338481651},
{"learn":[3.059970575],"iteration":986,"passed_time":0.9433879851,"remaining_time":0.0124255763},
{"learn":[3.059576341],"iteration":987,"passed_time":0.9440079208,"remaining_time":0.01146568325},
{"learn":[3.058175919],"iteration":988,"passed_time":0.9447815659,"remaining_time":0.01050818728},
{"learn":[3.056830702],"iteration":989,"passed_time":0.9454551926,"remaining_time":0.00955005245},
{"learn":[3.056336579],"iteration":990,"passed_time":0.9460269311,"remaining_time":0.008591566478},
{"learn":[3.055810414],"iteration":991,"passed_time":0.9466608294,"remaining_time":0.007634361527},
{"learn":[3.055476518],"iteration":992,"passed_time":0.9476453247,"remaining_time":0.006680279228},
{"learn":[3.053331734],"iteration":993,"passed_time":0.9487265024,"remaining_time":0.00572671933},
{"learn":[3.050890374],"iteration":994,"passed_time":0.9494530718,"remaining_time":0.004771120964},
{"learn":[3.04972623],"iteration":995,"passed_time":0.950103791,"remaining_time":0.003815677876},
{"learn":[3.047217327],"iteration":996,"passed_time":0.9507820345,"remaining_time":0.00286092889},
{"learn":[3.047155483],"iteration":997,"passed_time":0.9513552537,"remaining_time":0.001906523554},
{"learn":[3.04430671],"iteration":998,"passed_time":0.9519650132,"remaining_time":0.0009529179311},
{"learn":[3.042664195],"iteration":999,"passed_time":0.9526886752,"remaining_time":0}
]}